Panchul/unit7/fifo_using_pointer/fifo_using_pointer.sv
//  модуль очереди с использованием указателя
module      fifo_using_pointer #(
    parameter       DATA_WIDTH = 8,
    parameter       PTR_WIDTH = 2
) (
    //  тактирование
    input           clk,
    //  асинхронный сигнал сброса
    input           rst_n,
    //  сигнал записи
    input           push,
    //  сигнал чтения
    input           pop,
    //  данные на запись
    input           [(DATA_WIDTH - 1) : 0] write_data,
    //  прочитанные данные
    output          reg [(DATA_WIDTH - 1) : 0] read_data
);

//  сама очередь
reg                 [(DATA_WIDTH - 1) : 0] fifo[0 : (2**PTR_WIDTH - 1)];
//  указатель на место записи
reg                 [(PTR_WIDTH - 1) : 0] write_pointer;
//  указатель на место чтения
reg                 [(PTR_WIDTH - 1) : 0] read_pointer;

always      @(  posedge clk or negedge rst_n) begin
    if (    !rst_n) begin
        //  по сбросу указатели должны указывать на голову очереди
        write_pointer <= {PTR_WIDTH{1'b0}};
        read_pointer <= {PTR_WIDTH{1'b0}};
    end
    else begin
        if (    push) begin
            //  запись в очередь
            fifo[write_pointer] <= write_data;
            write_pointer <= write_pointer + 1;
        end

        if (    pop) begin
            //  чтение из очереди
            read_data <= fifo[read_pointer];
            read_pointer <= read_pointer + 1;
        end
    end
end

endmodule

Panchul/unit7/fifo_using_pointer/testbench.sv
`timescale 1ns / 1ns

module      testbench;

//  регистры для теста
reg         clk;
reg         reset;
reg         push;
reg         pop;
reg         [7:0] write_data;
wire        [7:0] read_data;

fifo_using_pointer #(
    .PTR_WIDTH(4),
    .DATA_WIDTH(8)
) dut (
    .clk(clk),
    .rst_n(~reset),
    .push(push),
    .pop(pop),
    .write_data(write_data),
    .read_data(read_data)
);

initial begin
    $dumpfile("wave.vcd");
    $dumpvars;
end

initial begin
    //  начальные значения
    clk = 1;
    reset = 1;
    push = 1;
    pop = 0;
    write_data = 8'b00000000;

    //  запись
    #20;    write_data = 8'b00000001;
    #10;    reset = 0;
    #10;    write_data = 8'b00000010;
    #20;    write_data = 8'b00000011;
    #20;    write_data = 8'b00000100;
    #20;    write_data = 8'b00000101;
    #20;    write_data = 8'b00000110;
    push = 0;
    pop = 1;
    #20;    write_data = 8'b00000111;
    #20;    write_data = 8'b00001000;
    #20;    write_data = 8'b00001001;
    #20;    write_data = 8'b00001011;

end

//  тактирование
always  #10 clk = ~clk;

//  окончание
initial begin
    #220;
    $finish;
end

endmodule

Panchul/unit7/fifo_using_pointer/wave.vcd
$date
	Sat Sep 12 12:01:43 2026
$end
$version
	Icarus Verilog
$end
$timescale
	1ns
$end
$scope module testbench $end
$var wire 8 ! read_data [7:0] $end
$var reg 1 " clk $end
$var reg 1 # pop $end
$var reg 1 $ push $end
$var reg 1 % reset $end
$var reg 8 & write_data [7:0] $end
$scope module dut $end
$var wire 1 " clk $end
$var wire 1 # pop $end
$var wire 1 $ push $end
$var wire 1 ' rst_n $end
$var wire 8 ( write_data [7:0] $end
$var reg 8 ) read_data [7:0] $end
$var reg 4 * read_pointer [3:0] $end
$var reg 4 + write_pointer [3:0] $end
$upscope $end
$upscope $end
$enddefinitions $end
#0
$dumpvars
b0 +
b0 *
bx )
b0 (
0'
b0 &
1%
1$
0#
1"
bx !
$end
#10
0"
#20
1"
b1 &
b1 (
#30
1'
0"
0%
#40
b1 +
1"
b10 &
b10 (
#50
0"
#60
b10 +
1"
b11 &
b11 (
#70
0"
#80
b11 +
1"
b100 &
b100 (
#90
0"
#100
b100 +
1"
b101 &
b101 (
#110
0"
#120
b1 *
b10 !
b10 )
1"
1#
0$
b110 &
b110 (
#130
0"
#140
b10 *
b11 !
b11 )
1"
b111 &
b111 (
#150
0"
#160
b11 *
b100 !
b100 )
1"
b1000 &
b1000 (
#170
0"
#180
b100 *
b101 !
b101 )
1"
b1001 &
b1001 (
#190
0"
#200
b101 *
bx !
bx )
1"
b1011 &
b1011 (
#210
0"
#220
b110 *
1"
