Panchul/unit8/fsm_lab8_1/fsm_lab8_1.sv
//  Пример КА Мура
module      fsm_lab_8_1 (
    //  тактирование
    input       clk,
    //  асинхронный сброс
    input       reset_n,
    //  сигнал разрешения работы
    input       enable,
    //  входной сигнал
    input       a,
    //  выходной сигнал
    output      y
);

//  описание возможных состояний
parameter       [1:0] S0 = 0, S1 = 1, S2 = 2;
//  текущее состояние
reg             [1:0] state;
//  следующее состояние
reg             [1:0] next_state;
    
//  описание послед части (регистра состояния)
always @(posedge clk or negedge reset_n) begin
    if (    !reset_n) begin
        //  при сбросе переход в состояние по умолчанию
        state <= S0;
    end
    else if (   enable) begin
        //  в штатном режиме (при разрешении работы)
        //  обновляется текущее состояние
        state <= next_state;
    end
end

//  логика вычисления следующего состояния
//  это комбинационная часть
always @(*) begin
    //  согласно графу, отталкиваемся от текущего состояния
    case (  state) 
    S0 :
        if (    a) begin
            next_state = S1;
        end 
        else begin
            next_state = S0;
        end
    S1 :
        if (    a) begin
            next_state = S2;
        end 
        else begin
            next_state = S1;
        end
    S2 :
        if (    a) begin
            next_state = S0;
        end 
        else begin
            next_state = S2;
        end
    default :
        //  страховка от нештатной ситуации
        next_state = S0;
    endcase
end

//  выходная логика с помощью непрерывного присваивания
assign  y = ((state == S2) || (state == S1));

endmodule

Panchul/unit8/fsm_lab8_1/testbench.sv
//  тестирование КА Мура
`timescale 1ns / 1ns

module      testbench;

//  сигналы для подключения к модулю
reg         clk;
reg         reset_n;
reg         enable;
reg         a;
wire        y;
wire        [1:0] state;

//  подключаемся к устройству
fsm_lab_8_1 dut(
    .clk(clk),
    .reset_n(reset_n),
    .enable(enable),
    .a(a),
    .y(y)
);

//  подключаемся к внутреннему reg устройства
assign  state = dut.state;

initial begin
    clk = 1;
    reset_n = 0;
    enable = 1;
    a = 1;
    #10; reset_n = 1;
    repeat (4) begin
        enable = 0;
        #20; a = 0;
        enable = 1;
        #20; a = 1;
        #20;
    end
end

//  тактирование
always begin
    #10;
    clk = ~clk;
end

initial begin
    #250;
    $finish;
end

initial begin
    $dumpfile("wave.vcd");
    $dumpvars;
end

endmodule

Panchul/unit8/fsm_lab8_1/wave.vcd
$date
	Sat Sep 19 19:43:22 2026
$end
$version
	Icarus Verilog
$end
$timescale
	1ns
$end
$scope module testbench $end
$var wire 2 ! state [1:0] $end
$var wire 1 " y $end
$var reg 1 # a $end
$var reg 1 $ clk $end
$var reg 1 % enable $end
$var reg 1 & reset_n $end
$scope module dut $end
$var wire 1 # a $end
$var wire 1 $ clk $end
$var wire 1 % enable $end
$var wire 1 & reset_n $end
$var wire 1 " y $end
$var reg 2 ' next_state [1:0] $end
$var reg 2 ( state [1:0] $end
$upscope $end
$upscope $end
$enddefinitions $end
#0
$dumpvars
b0 (
b1 '
0&
1%
1$
1#
0"
b0 !
$end
#10
0$
0%
1&
#20
1$
#30
b0 '
0$
1%
0#
#40
1$
#50
b1 '
0$
1#
#60
b10 '
1"
b1 !
b1 (
1$
#70
0$
0%
#80
1$
#90
b1 '
0$
1%
0#
#100
1$
#110
b10 '
0$
1#
#120
b0 '
b10 !
b10 (
1$
#130
0$
0%
#140
1$
#150
b10 '
0$
1%
0#
#160
1$
#170
b0 '
0$
1#
#180
b1 '
0"
b0 !
b0 (
1$
#190
0$
0%
#200
1$
#210
b0 '
0$
1%
0#
#220
1$
#230
b1 '
0$
1#
#240
b10 '
1"
b1 !
b1 (
1$
