Panchul/unit7/fifo_shift_reg/fifo_shift_reg.sv
//  реализация очереди с помощью сдвигового регистра
module      fifo_shift_reg #(
    parameter       DATA_WIDTH = 8,
    parameter       FIFO_SIZE = 4
) (
    //  сигнал тактирования
    input       clk,
    //  сигнал синхронного сброса
    input       reset,
    //  сигнал записи в стек
    input       push,
    //  сигнал чтения из стека
    input       pop,
    //  данные на входе стека
    input       [(DATA_WIDTH - 1) : 0] write_data,
    //  данные на выходе стека
    output      reg [(DATA_WIDTH - 1) : 0] read_data
);

//  непосредственно очередь
reg             [(DATA_WIDTH - 1) : 0] fifo[0 : (FIFO_SIZE - 1)];

integer         i;

always  @(posedge clk) begin
    //  синхронный сброс
    if (    reset) begin
        for (   i=0;    i < FIFO_SIZE;  i = i + 1) begin
            fifo[i] <= {DATA_WIDTH{1'b0}};
        end
    end
    else if (   push) begin //  сигнал записи
        //  запись осуществляется всегда в конец очереди
        //  сначала сдвигаем очередь вниз
        for (   i = 0; i < (FIFO_SIZE - 1) ; i = i + 1)
            fifo[i] <= fifo[i + 1];
        //  теперь пишем в самый конец
        fifo[FIFO_SIZE - 1] <= write_data;
    end
    else if (   pop) begin // сигнал чтения
        //  чтение читает всегда голову очереди
        read_data <= fifo[0];
        //  сдвигаем очередь вниз
        for (   i = 0; i < (FIFO_SIZE - 1) ; i = i + 1)
            fifo[i] <= fifo[i + 1];
    end
end

endmodule

Panchul/unit7/fifo_shift_reg/testbench.sv
`timescale 1ns / 1ns

module      testbench;

//  регистры для теста
reg         clk;
reg         reset;
reg         push;
reg         pop;
reg         [7:0] write_data;
wire        [7:0] read_data;

fifo_shift_reg #(
    .FIFO_SIZE(4),
    .DATA_WIDTH(8)
) dut (
    .clk(clk),
    .reset(reset),
    .push(push),
    .pop(pop),
    .write_data(write_data),
    .read_data(read_data)
);

initial begin
    $dumpfile("wave.vcd");
    $dumpvars;
end

initial begin
    //  начальные значения
    clk = 1;
    reset = 1;
    push = 1;
    pop = 0;
    write_data = 8'b00000000;

    //  запись
    #20;    write_data = 8'b00000001;
    #10;    reset = 0;
    #20;    write_data = 8'b00000010;
    #20;    write_data = 8'b00000011;
    #20;    write_data = 8'b00000100;
    #20;    write_data = 8'b00000101;
    #20;    write_data = 8'b00000110;
    push = 0;
    pop = 1;
    #20;    write_data = 8'b00000111;
    #20;    write_data = 8'b00001000;
    #20;    write_data = 8'b00001001;
    #20;    write_data = 8'b00001011;

end

//  тактирование
always  #10 clk = ~clk;

//  окончание
initial begin
    #220;
    $finish;
end

endmodule

Panchul/unit7/fifo_shift_reg/wave.vcd
$date
	Sat Sep 12 11:47:25 2026
$end
$version
	Icarus Verilog
$end
$timescale
	1ns
$end
$scope module testbench $end
$var wire 8 ! read_data [7:0] $end
$var reg 1 " clk $end
$var reg 1 # pop $end
$var reg 1 $ push $end
$var reg 1 % reset $end
$var reg 8 & write_data [7:0] $end
$scope module dut $end
$var wire 1 " clk $end
$var wire 1 # pop $end
$var wire 1 $ push $end
$var wire 1 % reset $end
$var wire 8 ' write_data [7:0] $end
$var reg 8 ( read_data [7:0] $end
$var integer 32 ) i [31:0] $end
$upscope $end
$upscope $end
$enddefinitions $end
#0
$dumpvars
b100 )
bx (
b0 '
b0 &
1%
1$
0#
1"
bx !
$end
#10
0"
#20
b100 )
1"
b1 &
b1 '
#30
0"
0%
#40
b11 )
1"
#50
0"
b10 &
b10 '
#60
b11 )
1"
#70
0"
b11 &
b11 '
#80
b11 )
1"
#90
0"
b100 &
b100 '
#100
b11 )
1"
#110
0"
b101 &
b101 '
#120
b11 )
1"
#130
0"
1#
0$
b110 &
b110 '
#140
b10 !
b10 (
b11 )
1"
#150
0"
b111 &
b111 '
#160
b11 !
b11 (
b11 )
1"
#170
0"
b1000 &
b1000 '
#180
b100 !
b100 (
b11 )
1"
#190
0"
b1001 &
b1001 '
#200
b101 !
b101 (
b11 )
1"
#210
0"
b1011 &
b1011 '
#220
b11 )
1"
