Panchul/unit5/shifter_mux/right_shifter_mux.sv
//  модуль сдвига вправо на мультиплексора
//  логического
//  на 8 бит
module      right_shifter_mux_8b (
    input   [7:0] data_in,
    input   [2:0] shift,
    output  reg [7:0] data_out
);

always @(*) begin
    case (shift)
        3'b001 :        data_out = {1'b0, data_in[7:1]};
        3'b010 :        data_out = {2'b0, data_in[7:2]};
        3'b011 :        data_out = {3'b0, data_in[7:3]};
        3'b100 :        data_out = {4'b0, data_in[7:4]};
        3'b101 :        data_out = {5'b0, data_in[7:5]};
        3'b110 :        data_out = {6'b0, data_in[7:6]};
        3'b111 :        data_out = {7'b0, data_in[7]};
        default :       data_out = data_in;
    endcase
end

endmodule

//  модуль сдвига вправо на мультиплексора
//  арифметического
//  на 8 бит
module      right_arith_shifter_mux_8b (
    input   [7:0] data_in,
    input   [2:0] shift,
    output  reg [7:0] data_out
);

always @(*) begin
    case (shift)
        3'b001 :        data_out = {data_in[7] ? 1'b1 : 1'b0, data_in[7:1]};
        3'b010 :        data_out = {data_in[7] ? {2{1'b1}} : 2'b0, data_in[7:2]};
        3'b011 :        data_out = {data_in[7] ? {3{1'b1}} : 3'b0, data_in[7:3]};
        3'b100 :        data_out = {data_in[7] ? {4{1'b1}} : 4'b0, data_in[7:4]};
        3'b101 :        data_out = {data_in[7] ? {5{1'b1}} : 5'b0, data_in[7:5]};
        3'b110 :        data_out = {data_in[7] ? {6{1'b1}} : 6'b0, data_in[7:6]};
        3'b111 :        data_out = {data_in[7] ? {7{1'b1}} : 7'b0, data_in[7]};
        default :       data_out = data_in;
    endcase
end

endmodule

//  модуль сдвига вправо на мультиплексора
//  логического
//  на 16 бит
module      right_shifter_mux_16b (
    input   [15:0] data_in,
    input   [3:0] shift,
    output  reg [15:0] data_out
);

always @(*) begin
    case (shift)
        4'b0001 :           data_out = {1'b0, data_in[15:1]};
        4'b0010 :           data_out = {2'b0, data_in[15:2]};
        4'b0011 :           data_out = {3'b0, data_in[15:3]};
        4'b0100 :           data_out = {4'b0, data_in[15:4]};
        4'b0101 :           data_out = {5'b0, data_in[15:5]};
        4'b0110 :           data_out = {6'b0, data_in[15:6]};
        4'b0111 :           data_out = {7'b0, data_in[15:7]};
        4'b1000 :           data_out = {8'b0, data_in[15:8]};
        4'b1001 :           data_out = {9'b0, data_in[15:9]};
        4'b1010 :           data_out = {10'b0, data_in[15:10]};
        4'b1011 :           data_out = {11'b0, data_in[15:11]};
        4'b1100 :           data_out = {12'b0, data_in[15:12]};
        4'b1101 :           data_out = {13'b0, data_in[15:13]};
        4'b1110 :           data_out = {14'b0, data_in[15:14]};
        4'b1111 :           data_out = {15'b0, data_in[15]};
        default :                   
                            data_out = data_in;
    endcase
end

endmodule

//  модуль сдвига вправо на мультиплексора
//  арифметического
//  на 16 бит
module      right_arith_shifter_mux_16b (
    input   [15:0] data_in,
    input   [3:0] shift,
    output  reg [15:0] data_out
);

always @(*) begin
    case (shift)
        4'b0001 :           data_out = {data_in[15] ? 1'b1 : 1'b0, data_in[15:1]};
        4'b0010 :           data_out = {data_in[15] ? {2{1'b1}} : 2'b0, data_in[15:2]};
        4'b0011 :           data_out = {data_in[15] ? {3{1'b1}} : 3'b0, data_in[15:3]};
        4'b0100 :           data_out = {data_in[15] ? {4{1'b1}} : 4'b0, data_in[15:4]};
        4'b0101 :           data_out = {data_in[15] ? {5{1'b1}} : 5'b0, data_in[15:5]};
        4'b0110 :           data_out = {data_in[15] ? {6{1'b1}} : 6'b0, data_in[15:6]};
        4'b0111 :           data_out = {data_in[15] ? {7{1'b1}} : 7'b0, data_in[15:7]};
        4'b1000 :           data_out = {data_in[15] ? {8{1'b1}} : 8'b0, data_in[15:8]};
        4'b1001 :           data_out = {data_in[15] ? {9{1'b1}} : 9'b0, data_in[15:9]};
        4'b1010 :           data_out = {data_in[15] ? {10{1'b1}} : 10'b0, data_in[15:10]};
        4'b1011 :           data_out = {data_in[15] ? {11{1'b1}} : 11'b0, data_in[15:11]};
        4'b1100 :           data_out = {data_in[15] ? {12{1'b1}} : 12'b0, data_in[15:12]};
        4'b1101 :           data_out = {data_in[15] ? {13{1'b1}} : 13'b0, data_in[15:13]};
        4'b1110 :           data_out = {data_in[15] ? {14{1'b1}} : 14'b0, data_in[15:14]};
        4'b1111 :           data_out = {data_in[15] ? {15{1'b1}} : 15'b0, data_in[15]};
        default :                   
                            data_out = data_in;
    endcase
end

endmodule

//  модуль сдвига вправо на мультиплексорах
//  логического
//  на 32 бит
module      right_shifter_mux_32b (
    input   [31:0] data_in,
    input   [4:0] shift,
    output  reg [31:0] data_out
);

always @(*) begin
    case (shift)
        5'b00001 :           data_out = {1'b0, data_in[31:1]};
        5'b00010 :           data_out = {2'b0, data_in[31:2]};
        5'b00011 :           data_out = {3'b0, data_in[31:3]};
        5'b00100 :           data_out = {4'b0, data_in[31:4]};
        5'b00101 :           data_out = {5'b0, data_in[31:5]};
        5'b00110 :           data_out = {6'b0, data_in[31:6]};
        5'b00111 :           data_out = {7'b0, data_in[31:7]};
        5'b01000 :           data_out = {8'b0, data_in[31:8]};
        5'b01001 :           data_out = {9'b0, data_in[31:9]};
        5'b01010 :           data_out = {10'b0, data_in[31:10]};
        5'b01011 :           data_out = {11'b0, data_in[31:11]};
        5'b01100 :           data_out = {12'b0, data_in[31:12]};
        5'b01101 :           data_out = {13'b0, data_in[31:13]};
        5'b01110 :           data_out = {14'b0, data_in[31:14]};
        5'b01111 :           data_out = {15'b0, data_in[31:15]};
        5'b10000 :           data_out = {16'b0, data_in[31:16]};
        5'b10001 :           data_out = {17'b0, data_in[31:17]};
        5'b10010 :           data_out = {18'b0, data_in[31:18]};
        5'b10011 :           data_out = {19'b0, data_in[31:19]};
        5'b10100 :           data_out = {20'b0, data_in[31:20]};
        5'b10101 :           data_out = {21'b0, data_in[31:21]};
        5'b10110 :           data_out = {22'b0, data_in[31:22]};
        5'b10111 :           data_out = {23'b0, data_in[31:23]};
        5'b11000 :           data_out = {24'b0, data_in[31:24]};
        5'b11001 :           data_out = {25'b0, data_in[31:25]};
        5'b11010 :           data_out = {26'b0, data_in[31:26]};
        5'b11011 :           data_out = {27'b0, data_in[31:27]};
        5'b11100 :           data_out = {28'b0, data_in[31:28]};
        5'b11101 :           data_out = {29'b0, data_in[31:29]};
        5'b11110 :           data_out = {30'b0, data_in[31:30]};
        5'b11111 :           data_out = {31'b0, data_in[31]};
        default :                   
                            data_out = data_in;
    endcase
end

endmodule


//  модуль сдвига вправо на мультиплексорах
//  арифметического
//  на 32 бит
module      right_arith_shifter_mux_32b (
    input   [31:0] data_in,
    input   [4:0] shift,
    output  reg [31:0] data_out
);

always @(*) begin
    case (shift)
        5'b00001 :           data_out = {data_in[31] ? 1'b1 : 1'b0, data_in[31:1]};
        5'b00010 :           data_out = {data_in[31] ? {2{1'b1}} : 2'b0, data_in[31:2]};
        5'b00011 :           data_out = {data_in[31] ? {3{1'b1}} : 3'b0, data_in[31:3]};
        5'b00100 :           data_out = {data_in[31] ? {4{1'b1}} : 4'b0, data_in[31:4]};
        5'b00101 :           data_out = {data_in[31] ? {5{1'b1}} : 5'b0, data_in[31:5]};
        5'b00110 :           data_out = {data_in[31] ? {6{1'b1}} : 6'b0, data_in[31:6]};
        5'b00111 :           data_out = {data_in[31] ? {7{1'b1}} : 7'b0, data_in[31:7]};
        5'b01000 :           data_out = {data_in[31] ? {8{1'b1}} : 8'b0, data_in[31:8]};
        5'b01001 :           data_out = {data_in[31] ? {9{1'b1}} : 9'b0, data_in[31:9]};
        5'b01010 :           data_out = {data_in[31] ? {10{1'b1}} : 10'b0, data_in[31:10]};
        5'b01011 :           data_out = {data_in[31] ? {11{1'b1}} : 11'b0, data_in[31:11]};
        5'b01100 :           data_out = {data_in[31] ? {12{1'b1}} : 12'b0, data_in[31:12]};
        5'b01101 :           data_out = {data_in[31] ? {13{1'b1}} : 13'b0, data_in[31:13]};
        5'b01110 :           data_out = {data_in[31] ? {14{1'b1}} : 14'b0, data_in[31:14]};
        5'b01111 :           data_out = {data_in[31] ? {15{1'b1}} : 15'b0, data_in[31:15]};
        5'b10000 :           data_out = {data_in[31] ? {16{1'b1}} : 16'b0, data_in[31:16]};
        5'b10001 :           data_out = {data_in[31] ? {17{1'b1}} : 17'b0, data_in[31:17]};
        5'b10010 :           data_out = {data_in[31] ? {18{1'b1}} : 18'b0, data_in[31:18]};
        5'b10011 :           data_out = {data_in[31] ? {19{1'b1}} : 19'b0, data_in[31:19]};
        5'b10100 :           data_out = {data_in[31] ? {20{1'b1}} : 20'b0, data_in[31:20]};
        5'b10101 :           data_out = {data_in[31] ? {21{1'b1}} : 21'b0, data_in[31:21]};
        5'b10110 :           data_out = {data_in[31] ? {22{1'b1}} : 22'b0, data_in[31:22]};
        5'b10111 :           data_out = {data_in[31] ? {23{1'b1}} : 23'b0, data_in[31:23]};
        5'b11000 :           data_out = {data_in[31] ? {24{1'b1}} : 24'b0, data_in[31:24]};
        5'b11001 :           data_out = {data_in[31] ? {25{1'b1}} : 25'b0, data_in[31:25]};
        5'b11010 :           data_out = {data_in[31] ? {26{1'b1}} : 26'b0, data_in[31:26]};
        5'b11011 :           data_out = {data_in[31] ? {27{1'b1}} : 27'b0, data_in[31:27]};
        5'b11100 :           data_out = {data_in[31] ? {28{1'b1}} : 28'b0, data_in[31:28]};
        5'b11101 :           data_out = {data_in[31] ? {29{1'b1}} : 29'b0, data_in[31:29]};
        5'b11110 :           data_out = {data_in[31] ? {30{1'b1}} : 30'b0, data_in[31:30]};
        5'b11111 :           data_out = {data_in[31] ? {31{1'b1}} : 31'b0, data_in[31]};
        default :                   
                            data_out = data_in;
    endcase
end

endmodule

Panchul/unit5/shifter_mux/left_shifter_mux.sv
//  модуль сдвига влево на мультиплексора
//  логического и арифметического (это одно и то же)
//  на 8 бит
module      left_shifter_mux_8b (
    input   [7:0] data_in,
    input   [2:0] shift,
    output  reg [7:0] data_out
);

always @(*) begin
    case (shift)
        3'b001 :        data_out = {data_in[6:0], 1'b0};
        3'b010 :        data_out = {data_in[5:0], 2'b0};
        3'b011 :        data_out = {data_in[4:0], 3'b0};
        3'b100 :        data_out = {data_in[3:0], 4'b0};
        3'b101 :        data_out = {data_in[2:0], 5'b0};
        3'b110 :        data_out = {data_in[1:0], 6'b0};
        3'b111 :        data_out = {data_in[0], 7'b0};
        default :       data_out = data_in;
    endcase
end

endmodule

//  модуль сдвига влево на мультиплексора
//  логического и арифметического (это одно и то же)
//  на 16 бит
module      left_shifter_mux_16b (
    input   [15:0] data_in,
    input   [3:0] shift,
    output  reg [15:0] data_out
);

always @(*) begin
    case (shift)
        4'b0001 :           data_out = {data_in[14:0], 1'b0};
        4'b0010 :           data_out = {data_in[13:0], 2'b0};
        4'b0011 :           data_out = {data_in[12:0], 3'b0};
        4'b0100 :           data_out = {data_in[11:0], 4'b0};
        4'b0101 :           data_out = {data_in[10:0], 5'b0};
        4'b0110 :           data_out = {data_in[9:0], 6'b0};
        4'b0111 :           data_out = {data_in[8:0], 7'b0};
        4'b1000 :           data_out = {data_in[7:0], 8'b0};
        4'b1001 :           data_out = {data_in[6:0], 9'b0};
        4'b1010 :           data_out = {data_in[5:0], 10'b0};
        4'b1011 :           data_out = {data_in[4:0], 11'b0};
        4'b1100 :           data_out = {data_in[3:0], 12'b0};
        4'b1101 :           data_out = {data_in[2:0], 13'b0};
        4'b1110 :           data_out = {data_in[1:0], 14'b0};
        4'b1111 :           data_out = {data_in[0], 15'b0};
        default :                   
                            data_out = data_in;
    endcase
end

endmodule

//  модуль сдвига влево на мультиплексора
//  логического и арифметического (это одно и то же)
//  на 32 бит
module      left_shifter_mux_32b (
    input   [31:0] data_in,
    input   [4:0] shift,
    output  reg [31:0] data_out
);

always @(*) begin
    case (shift)
        5'b00001 :           data_out = {data_in[30:0], 1'b0};
        5'b00010 :           data_out = {data_in[29:0], 2'b0};
        5'b00011 :           data_out = {data_in[28:0], 3'b0};
        5'b00100 :           data_out = {data_in[27:0], 4'b0};
        5'b00101 :           data_out = {data_in[26:0], 5'b0};
        5'b00110 :           data_out = {data_in[25:0], 6'b0};
        5'b00111 :           data_out = {data_in[24:0], 7'b0};
        5'b01000 :           data_out = {data_in[23:0], 8'b0};
        5'b01001 :           data_out = {data_in[22:0], 9'b0};
        5'b01010 :           data_out = {data_in[21:0], 10'b0};
        5'b01011 :           data_out = {data_in[20:0], 11'b0};
        5'b01100 :           data_out = {data_in[19:0], 12'b0};
        5'b01101 :           data_out = {data_in[18:0], 13'b0};
        5'b01110 :           data_out = {data_in[17:0], 14'b0};
        5'b01111 :           data_out = {data_in[16:0], 15'b0};
        5'b10000 :           data_out = {data_in[15:0], 16'b0};
        5'b10001 :           data_out = {data_in[14:0], 17'b0};
        5'b10010 :           data_out = {data_in[13:0], 18'b0};
        5'b10011 :           data_out = {data_in[12:0], 19'b0};
        5'b10100 :           data_out = {data_in[11:0], 20'b0};
        5'b10101 :           data_out = {data_in[10:0], 21'b0};
        5'b10110 :           data_out = {data_in[9:0], 22'b0};
        5'b10111 :           data_out = {data_in[8:0], 23'b0};
        5'b11000 :           data_out = {data_in[7:0], 24'b0};
        5'b11001 :           data_out = {data_in[6:0], 25'b0};
        5'b11010 :           data_out = {data_in[5:0], 26'b0};
        5'b11011 :           data_out = {data_in[4:0], 27'b0};
        5'b11100 :           data_out = {data_in[3:0], 28'b0};
        5'b11101 :           data_out = {data_in[2:0], 29'b0};
        5'b11110 :           data_out = {data_in[1:0], 30'b0};
        5'b11111 :           data_out = {data_in[0], 31'b0};
        default :                   
                            data_out = data_in;
    endcase
end

endmodule

Panchul/unit5/shifter_mux/testbench.sv
`timescale 1ns / 1ps

`define     TEST_NUMBER 10

module      testbench;

reg     [7:0] data_8b_in;
reg     [2:0] shift_8b;

reg     [15:0] data_16b_in;
reg     [3:0] shift_16b;

reg     [31:0] data_32b_in;
reg     [4:0] shift_32b;

wire    [7:0] data_lsh_8b_out;
wire    [15:0] data_lsh_16b_out;
wire    [31:0] data_lsh_32b_out;

reg     [7:0] ideal_data_lsh_8b_out;
reg     [15:0] ideal_data_lsh_16b_out;
reg     [31:0] ideal_data_lsh_32b_out;

wire    [7:0] data_rsh_8b_out;
wire    [15:0] data_rsh_16b_out;
wire    [31:0] data_rsh_32b_out;

reg     [7:0] ideal_data_rsh_8b_out;
reg     [15:0] ideal_data_rsh_16b_out;
reg     [31:0] ideal_data_rsh_32b_out;

wire    [7:0] data_arsh_8b_out;
wire    [15:0] data_arsh_16b_out;
wire    [31:0] data_arsh_32b_out;

reg     [7:0] ideal_data_arsh_8b_out;
reg     [15:0] ideal_data_arsh_16b_out;
reg     [31:0] ideal_data_arsh_32b_out;

reg     [31:0] i;

initial begin
    $dumpfile("wave.vcd");
    $dumpvars;
end

// ---------------------------------
left_shifter_mux_8b lsh_8b(
    .data_in(data_8b_in),
    .shift(shift_8b),
    .data_out(data_lsh_8b_out)
);

left_shifter_mux_16b lsh_16b(
    .data_in(data_16b_in),
    .shift(shift_16b),
    .data_out(data_lsh_16b_out)
);

left_shifter_mux_32b lsh_32b(
    .data_in(data_32b_in),
    .shift(shift_32b),
    .data_out(data_lsh_32b_out)
);

// -----------------------------------
right_shifter_mux_8b rsh_8b(
    .data_in(data_8b_in),
    .shift(shift_8b),
    .data_out(data_rsh_8b_out)
);

right_shifter_mux_16b rsh_16b(
    .data_in(data_16b_in),
    .shift(shift_16b),
    .data_out(data_rsh_16b_out)
);

right_shifter_mux_32b rsh_32b(
    .data_in(data_32b_in),
    .shift(shift_32b),
    .data_out(data_rsh_32b_out)
);

// ---------------------------------
right_arith_shifter_mux_8b arsh_8b(
    .data_in(data_8b_in),
    .shift(shift_8b),
    .data_out(data_arsh_8b_out)
);

right_arith_shifter_mux_16b arsh_16b(
    .data_in(data_16b_in),
    .shift(shift_16b),
    .data_out(data_arsh_16b_out)
);

right_arith_shifter_mux_32b arsh_32b(
    .data_in(data_32b_in),
    .shift(shift_32b),
    .data_out(data_arsh_32b_out)
);

initial begin
    for(i = 0; i <= 9; i = i + 1) begin
        data_8b_in = $urandom_range(1 << 8 - 1, 0);
        data_16b_in = $urandom_range(1 << 16 - 1, 0);
        data_32b_in = $urandom_range(1 << 32 - 1, 0);

        shift_8b = $urandom_range(1 << 3 - 1, 0);
        shift_16b = $urandom_range(1 << 4 - 1, 0);
        shift_32b = $urandom_range(1 << 5 - 1, 0);

        ideal_data_lsh_8b_out = data_8b_in << shift_8b;
        ideal_data_lsh_16b_out = data_16b_in << shift_16b;
        ideal_data_lsh_32b_out = data_32b_in << shift_32b;

        ideal_data_rsh_8b_out = data_8b_in >> shift_8b;
        ideal_data_rsh_16b_out = data_16b_in >> shift_16b;
        ideal_data_rsh_32b_out = data_32b_in >> shift_32b;

        ideal_data_arsh_8b_out = data_8b_in >>> shift_8b;
        ideal_data_arsh_16b_out = data_16b_in >>> shift_16b;
        ideal_data_arsh_32b_out = data_32b_in >>> shift_32b;

        #5;

        //  сравнение результатов
        if (ideal_data_lsh_8b_out != data_lsh_8b_out) begin
            $display("%d << %d = %d != %d\n", 
                data_8b_in, 
                shift_8b, 
                data_lsh_8b_out, 
                ideal_data_lsh_8b_out);
            $finish;
        end

        if (ideal_data_lsh_16b_out != data_lsh_16b_out) begin
            $display("%d << %d = %d != %d\n", 
                data_16b_in, 
                shift_16b, 
                data_lsh_16b_out, 
                ideal_data_lsh_16b_out);
            $finish;
        end

        if (ideal_data_lsh_32b_out != data_lsh_32b_out) begin
            $display("%d << %d = %d != %d\n", 
                data_32b_in, 
                shift_32b, 
                data_lsh_32b_out, 
                ideal_data_lsh_32b_out);
            $finish;
        end

        // ///
        if (ideal_data_rsh_8b_out != data_rsh_8b_out) begin
            $display("%d >> %d = %d != %d\n", 
                data_8b_in, 
                shift_8b, 
                data_rsh_8b_out, 
                ideal_data_rsh_8b_out);
            $finish;
        end

        if (ideal_data_rsh_16b_out != data_rsh_16b_out) begin
            $display("%d >> %d = %d != %d\n", 
                data_16b_in, 
                shift_16b, 
                data_rsh_16b_out, 
                ideal_data_rsh_16b_out);
            $finish;
        end

        if (ideal_data_rsh_32b_out != data_rsh_32b_out) begin
            $display("%d << %d = %d != %d\n", 
                data_32b_in, 
                shift_32b, 
                data_rsh_32b_out, 
                ideal_data_rsh_32b_out);
            $finish;
        end

        // ///
        if (ideal_data_arsh_8b_out != data_arsh_8b_out) begin
            $display("%d >>> %d = %d != %d\n", 
                data_8b_in, 
                shift_8b, 
                data_arsh_8b_out, 
                ideal_data_arsh_8b_out);
            $finish;
        end

        if (ideal_data_arsh_16b_out != data_arsh_16b_out) begin
            $display("%d >> %d = %d != %d\n", 
                data_16b_in, 
                shift_16b, 
                data_arsh_16b_out, 
                ideal_data_arsh_16b_out);
            $finish;
        end

        if (ideal_data_arsh_32b_out != data_arsh_32b_out) begin
            $display("%d << %d = %d != %d\n", 
                data_32b_in, 
                shift_32b, 
                data_arsh_32b_out, 
                ideal_data_arsh_32b_out);
            $finish;
        end

        #10;
    end
    $display("Tests have been finished\n");
    $finish;
end

endmodule

Panchul/unit5/shifter_mux/wave.vcd
$date
	Thu Aug  6 17:07:01 2026
$end
$version
	Icarus Verilog
$end
$timescale
	1ps
$end
$scope module testbench $end
$var wire 8 ! data_rsh_8b_out [7:0] $end
$var wire 32 " data_rsh_32b_out [31:0] $end
$var wire 16 # data_rsh_16b_out [15:0] $end
$var wire 8 $ data_lsh_8b_out [7:0] $end
$var wire 32 % data_lsh_32b_out [31:0] $end
$var wire 16 & data_lsh_16b_out [15:0] $end
$var wire 8 ' data_arsh_8b_out [7:0] $end
$var wire 32 ( data_arsh_32b_out [31:0] $end
$var wire 16 ) data_arsh_16b_out [15:0] $end
$var reg 16 * data_16b_in [15:0] $end
$var reg 32 + data_32b_in [31:0] $end
$var reg 8 , data_8b_in [7:0] $end
$var reg 32 - i [31:0] $end
$var reg 16 . ideal_data_arsh_16b_out [15:0] $end
$var reg 32 / ideal_data_arsh_32b_out [31:0] $end
$var reg 8 0 ideal_data_arsh_8b_out [7:0] $end
$var reg 16 1 ideal_data_lsh_16b_out [15:0] $end
$var reg 32 2 ideal_data_lsh_32b_out [31:0] $end
$var reg 8 3 ideal_data_lsh_8b_out [7:0] $end
$var reg 16 4 ideal_data_rsh_16b_out [15:0] $end
$var reg 32 5 ideal_data_rsh_32b_out [31:0] $end
$var reg 8 6 ideal_data_rsh_8b_out [7:0] $end
$var reg 4 7 shift_16b [3:0] $end
$var reg 5 8 shift_32b [4:0] $end
$var reg 3 9 shift_8b [2:0] $end
$scope module arsh_16b $end
$var wire 16 : data_in [15:0] $end
$var wire 4 ; shift [3:0] $end
$var reg 16 < data_out [15:0] $end
$upscope $end
$scope module arsh_32b $end
$var wire 32 = data_in [31:0] $end
$var wire 5 > shift [4:0] $end
$var reg 32 ? data_out [31:0] $end
$upscope $end
$scope module arsh_8b $end
$var wire 8 @ data_in [7:0] $end
$var wire 3 A shift [2:0] $end
$var reg 8 B data_out [7:0] $end
$upscope $end
$scope module lsh_16b $end
$var wire 16 C data_in [15:0] $end
$var wire 4 D shift [3:0] $end
$var reg 16 E data_out [15:0] $end
$upscope $end
$scope module lsh_32b $end
$var wire 32 F data_in [31:0] $end
$var wire 5 G shift [4:0] $end
$var reg 32 H data_out [31:0] $end
$upscope $end
$scope module lsh_8b $end
$var wire 8 I data_in [7:0] $end
$var wire 3 J shift [2:0] $end
$var reg 8 K data_out [7:0] $end
$upscope $end
$scope module rsh_16b $end
$var wire 16 L data_in [15:0] $end
$var wire 4 M shift [3:0] $end
$var reg 16 N data_out [15:0] $end
$upscope $end
$scope module rsh_32b $end
$var wire 32 O data_in [31:0] $end
$var wire 5 P shift [4:0] $end
$var reg 32 Q data_out [31:0] $end
$upscope $end
$scope module rsh_8b $end
$var wire 8 R data_in [7:0] $end
$var wire 3 S shift [2:0] $end
$var reg 8 T data_out [7:0] $end
$upscope $end
$upscope $end
$enddefinitions $end
#0
$dumpvars
b1001001 T
b0 S
b1001001 R
b0 Q
b1000 P
b0 O
b1000000100010 N
b1 M
b10000001000100 L
b1001001 K
b0 J
b1001001 I
b0 H
b1000 G
b0 F
b100000010001000 E
b1 D
b10000001000100 C
b1001001 B
b0 A
b1001001 @
b0 ?
b1000 >
b0 =
b1000000100010 <
b1 ;
b10000001000100 :
b0 9
b1000 8
b1 7
b1001001 6
b0 5
b1000000100010 4
b1001001 3
b0 2
b100000010001000 1
b1001001 0
b0 /
b1000000100010 .
b0 -
b1001001 ,
b0 +
b10000001000100 *
b1000000100010 )
b0 (
b1001001 '
b100000010001000 &
b0 %
b1001001 $
b1000000100010 #
b0 "
b1001001 !
$end
#15000
b1001011000010000 &
b1001011000010000 E
b110010110 #
b110010110 N
b110010110 )
b110010110 <
b1100100 $
b1100100 K
b1100100 !
b1100100 T
b1100100 '
b1100100 B
b110010110 .
b1100100 0
b110010110 4
b1100100 6
b1001011000010000 1
b1100100 3
b100 7
b100 ;
b100 D
b100 M
b1100101100001 *
b1100101100001 :
b1100101100001 C
b1100101100001 L
b1100100 ,
b1100100 @
b1100100 I
b1100100 R
b1 -
#30000
b100111101 )
b100111101 <
b100111101 #
b100111101 N
b1101000111000000 &
b1101000111000000 E
b101 '
b101 B
b101 !
b101 T
b11100000 $
b11100000 K
b100111101 .
b101 0
b100111101 4
b101 6
b1101000111000000 1
b11100000 3
b10000 8
b10000 >
b10000 G
b10000 P
b110 7
b110 ;
b110 D
b110 M
b100 9
b100 A
b100 J
b100 S
b100111101000111 *
b100111101000111 :
b100111101000111 C
b100111101000111 L
b1011110 ,
b1011110 @
b1011110 I
b1011110 R
b10 -
#45000
b111110000000000 &
b111110000000000 E
b110001 #
b110001 N
b110001 )
b110001 <
b1100010 $
b1100010 K
b11000 !
b11000 T
b11000 '
b11000 B
b110001 .
b11000 0
b110001 4
b11000 6
b111110000000000 1
b1100010 3
b11 8
b11 >
b11 G
b11 P
b1000 7
b1000 ;
b1000 D
b1000 M
b1 9
b1 A
b1 J
b1 S
b11000101111100 *
b11000101111100 :
b11000101111100 C
b11000101111100 L
b110001 ,
b110001 @
b110001 I
b110001 R
b11 -
#60000
b110001111110 )
b110001111110 <
b110001111110 #
b110001111110 N
b1111110111000 &
b1111110111000 E
b0 '
b0 B
b0 !
b0 T
b1000000 $
b1000000 K
b110001111110 .
b0 0
b110001111110 4
b0 6
b1111110111000 1
b1000000 3
b111 8
b111 >
b111 G
b111 P
b11 7
b11 ;
b11 D
b11 M
b100 9
b100 A
b100 J
b100 S
b110001111110111 *
b110001111110111 :
b110001111110111 C
b110001111110111 L
b100 ,
b100 @
b100 I
b100 R
b100 -
#75000
b101011100101100 &
b101011100101100 E
b101011100101100 #
b101011100101100 N
b101011100101100 )
b101011100101100 <
b1100010 $
b1100010 K
b11000 !
b11000 T
b11000 '
b11000 B
b101011100101100 .
b11000 0
b101011100101100 4
b11000 6
b101011100101100 1
b1100010 3
b11 8
b11 >
b11 G
b11 P
b0 7
b0 ;
b0 D
b0 M
b1 9
b1 A
b1 J
b1 S
b101011100101100 *
b101011100101100 :
b101011100101100 C
b101011100101100 L
b110001 ,
b110001 @
b110001 I
b110001 R
b101 -
#90000
b1000010101 )
b1000010101 <
b1000010101 #
b1000010101 N
b101011101000000 &
b101011101000000 E
b1100 '
b1100 B
b1100 !
b1100 T
b110010 $
b110010 K
b1000010101 .
b1100 0
b1000010101 4
b1100 6
b101011101000000 1
b110010 3
b1110 8
b1110 >
b1110 G
b1110 P
b101 7
b101 ;
b101 D
b101 M
b100001010111010 *
b100001010111010 :
b100001010111010 C
b100001010111010 L
b11001 ,
b11001 @
b11001 I
b11001 R
b110 -
#105000
b10010110010000 &
b10010110010000 E
b10010110010000 #
b10010110010000 N
b10010110010000 )
b10010110010000 <
b100111 $
b100111 K
b100111 !
b100111 T
b100111 '
b100111 B
b10010110010000 .
b100111 0
b10010110010000 4
b100111 6
b10010110010000 1
b100111 3
b10 8
b10 >
b10 G
b10 P
b0 7
b0 ;
b0 D
b0 M
b0 9
b0 A
b0 J
b0 S
b10010110010000 *
b10010110010000 :
b10010110010000 C
b10010110010000 L
b100111 ,
b100111 @
b100111 I
b100111 R
b111 -
#120000
b11010101010 )
b11010101010 <
b11010101010 #
b11010101010 N
b1010101010011000 &
b1010101010011000 E
b1011011 '
b1011011 B
b1011011 !
b1011011 T
b1011011 $
b1011011 K
b11010101010 .
b1011011 0
b11010101010 4
b1011011 6
b1010101010011000 1
b1011011 3
b1001 8
b1001 >
b1001 G
b1001 P
b11 7
b11 ;
b11 D
b11 M
b11010101010011 *
b11010101010011 :
b11010101010011 C
b11010101010011 L
b1011011 ,
b1011011 @
b1011011 I
b1011011 R
b1000 -
#135000
b100011000010000 &
b100011000010000 E
b100100011000 #
b100100011000 N
b100100011000 )
b100100011000 <
b11010000 $
b11010000 K
b1101 !
b1101 T
b1101 '
b1101 B
b100100011000 .
b1101 0
b100100011000 4
b1101 6
b100011000010000 1
b11010000 3
b10 8
b10 >
b10 G
b10 P
b10 9
b10 A
b10 J
b10 S
b100100011000010 *
b100100011000010 :
b100100011000010 C
b100100011000010 L
b110100 ,
b110100 @
b110100 I
b110100 R
b1001 -
#150000
b1010 -
