Panchul/unit6/updown_counter/updown_counter.sv
//  счетчик с управляемым направление счета
module      updown_counter #(
    parameter       WIDTH = 8
) (
    input       clk,
    input       rst_n,
    input       up_down,
    output      reg [WIDTH-1 : 0] cnt
);

always @(posedge clk or negedge rst_n) begin
    if (!rst_n)
        cnt <= {WIDTH{1'b0}};
    else if (!up_down)
        cnt <= cnt + 1'b1;
    else
        cnt <= cnt - 1'b1;
end

endmodule

Panchul/unit6/updown_counter/testbench.sv
`timescale 1ns / 1ps

module testbench;

reg         clk;
reg         rst_n;
reg         up_down;
wire        [7:0] cnt;

initial begin
    $dumpfile("wave.vcd");
    $dumpvars;
end

updown_counter #(
    .WIDTH(8)
) dut (
    .clk(clk),
    .rst_n(rst_n),
    .up_down(up_down),
    .cnt(cnt)
);

initial begin
    clk = 0;
    forever begin
        #10;
        clk = ~clk;
    end
end

initial begin
    rst_n = 0;
    up_down = 0;
    #25;
    rst_n = 1;
    #47;
    up_down = 1;
    #56;
    up_down = 0;
    #71;
    $display("TEST OK");
    $finish;
end

endmodule

Panchul/unit6/updown_counter/wave.vcd
$date
	Thu Aug 13 05:21:56 2026
$end
$version
	Icarus Verilog
$end
$timescale
	1ps
$end
$scope module testbench $end
$var wire 8 ! cnt [7:0] $end
$var reg 1 " clk $end
$var reg 1 # rst_n $end
$var reg 1 $ up_down $end
$scope module dut $end
$var wire 1 " clk $end
$var wire 1 # rst_n $end
$var wire 1 $ up_down $end
$var reg 8 % cnt [7:0] $end
$upscope $end
$upscope $end
$enddefinitions $end
#0
$dumpvars
b0 %
0$
0#
0"
b0 !
$end
#10000
1"
#20000
0"
#25000
1#
#30000
b1 !
b1 %
1"
#40000
0"
#50000
b10 !
b10 %
1"
#60000
0"
#70000
b11 !
b11 %
1"
#72000
1$
#80000
0"
#90000
b10 !
b10 %
1"
#100000
0"
#110000
b1 !
b1 %
1"
#120000
0"
#128000
0$
#130000
b10 !
b10 %
1"
#140000
0"
#150000
b11 !
b11 %
1"
#160000
0"
#170000
b100 !
b100 %
1"
#180000
0"
#190000
b101 !
b101 %
1"
