Panchul/unit7/reg_file/reg_file.sv
//  кирпичик регистрового файла - регистр
module register #(
    parameter SIZE = 4
) (
    input       ena,
    input       clk,
    input       [SIZE - 1 : 0] d,
    output      reg [SIZE - 1 : 0] q
);


always @(posedge clk) begin

    if (ena)
        q <= d;

end


endmodule

//  непосредственно регистровый файл для 4 регистров
module reg_file #(
    parameter       DATA_WIDTH = 4
) (
    input       clk,
    input       we,
    input       [1 : 0] addr,
    input       [DATA_WIDTH - 1 : 0] data_in,
    output      [DATA_WIDTH - 1 : 0] data_out
);

//  write_en для каждого из регистров
reg         [3 : 0] w_we;
//  сигнал от выходного мультиплексора
//  ЧТО было выбрано
reg         [DATA_WIDTH - 1 : 0] mux_out;

//  выводы с каждого регистра 
//  всего будет 4 выходных порта
//  шириной DATA_WIDTH бит
wire        [DATA_WIDTH - 1 : 0] reg0;
wire        [DATA_WIDTH - 1 : 0] reg1;
wire        [DATA_WIDTH - 1 : 0] reg2;
wire        [DATA_WIDTH - 1 : 0] reg3;

//  спец шина для объединения we и addr
//  чтобы исключить x варианты
wire        [2 : 0] mux_in;

assign mux_in = {   we, addr};

//  управление шиной write_enable
//  ЗАПИСЬ данных в рег файл
always @(*) begin
    //  это комб логика
    case (mux_in)
        3'b1_00 :       w_we = 4'b0001;
        3'b1_01 :       w_we = 4'b0010;
        3'b1_10 :       w_we = 4'b0100;
        3'b1_11 :       w_we = 4'b1000;
        default :       w_we = 4'b0000;
    endcase

end

//  управление выходным мультиплексором
//  ЧТЕНИЕ данных из рег файла
always @(*) begin
    //  это также комб логика
    //  выбор ОТКУДА читать данные
    case (  addr)
        2'b00 :     mux_out = reg0;
        2'b01 :     mux_out = reg1;
        2'b10 :     mux_out = reg2;
        2'b11 :     mux_out = reg3;
        default :   mux_out = {DATA_WIDTH{1'b0}};
    endcase
end

//  подключение выхода
assign      data_out = mux_out;

//  соединение регистров
register #(DATA_WIDTH) register0(
    .ena(w_we[0]),
    .clk(clk),
    .d(data_in),
    .q(reg0)
);

register #(DATA_WIDTH) register1(
    .ena(w_we[1]),
    .clk(clk),
    .d(data_in),
    .q(reg1)
);

register #(DATA_WIDTH) register2(
    .ena(w_we[2]),
    .clk(clk),
    .d(data_in),
    .q(reg2)
);

register #(DATA_WIDTH) register3(
    .ena(w_we[3]),
    .clk(clk),
    .d(data_in),
    .q(reg3)
);


endmodule

Panchul/unit7/reg_file/testbench.sv
//  непосредственно тестирование регистрового файла
`timescale 1ns / 1ns

module      testbench;

//  входные и выходные сигналы
reg     clk;
reg     we;
reg     [1:0] addr;
reg     [3:0] data_in;
wire    [3:0] data_out;

reg_file    #(
    .DATA_WIDTH(4)
) dut (
    .clk(clk),
    .we(we),
    .addr(addr),
    .data_in(data_in),
    .data_out(data_out)
);

initial begin

    clk = 1;
    we = 1'b1;
    addr = 2'b00;
    data_in = 4'b1111;

    #5;

    repeat(3) begin
        #20;
        addr = addr + 2'b01;
    end

    #40;
    we = 1'b0;
    addr = 2'b00;
    data_in = 4'b0000;

    repeat(3) begin
        #20;
        addr = addr + 2'b01;
    end

end

//  тактовый сигнал
always #10 clk = ~clk;

//  запуск, 200 тактов и стоп
initial begin
    #200;
    $finish;
end

initial begin
    $dumpfile("wave.vcd");
    $dumpvars;
end

endmodule

Panchul/unit7/reg_file/wave.vcd
$date
	Sun Aug 30 20:37:03 2026
$end
$version
	Icarus Verilog
$end
$timescale
	1ns
$end
$scope module testbench $end
$var wire 4 ! data_out [3:0] $end
$var reg 2 " addr [1:0] $end
$var reg 1 # clk $end
$var reg 4 $ data_in [3:0] $end
$var reg 1 % we $end
$scope module dut $end
$var wire 2 & addr [1:0] $end
$var wire 1 # clk $end
$var wire 4 ' data_in [3:0] $end
$var wire 4 ( data_out [3:0] $end
$var wire 1 % we $end
$var wire 4 ) reg3 [3:0] $end
$var wire 4 * reg2 [3:0] $end
$var wire 4 + reg1 [3:0] $end
$var wire 4 , reg0 [3:0] $end
$var wire 3 - mux_in [2:0] $end
$var parameter 32 . DATA_WIDTH $end
$var reg 4 / mux_out [3:0] $end
$var reg 4 0 w_we [3:0] $end
$scope module register0 $end
$var wire 1 # clk $end
$var wire 4 1 d [3:0] $end
$var wire 1 2 ena $end
$var parameter 32 3 SIZE $end
$var reg 4 4 q [3:0] $end
$upscope $end
$scope module register1 $end
$var wire 1 # clk $end
$var wire 4 5 d [3:0] $end
$var wire 1 6 ena $end
$var parameter 32 7 SIZE $end
$var reg 4 8 q [3:0] $end
$upscope $end
$scope module register2 $end
$var wire 1 # clk $end
$var wire 4 9 d [3:0] $end
$var wire 1 : ena $end
$var parameter 32 ; SIZE $end
$var reg 4 < q [3:0] $end
$upscope $end
$scope module register3 $end
$var wire 1 # clk $end
$var wire 4 = d [3:0] $end
$var wire 1 > ena $end
$var parameter 32 ? SIZE $end
$var reg 4 @ q [3:0] $end
$upscope $end
$upscope $end
$upscope $end
$enddefinitions $end
$comment Show the parameter values. $end
$dumpall
b100 ?
b100 ;
b100 7
b100 3
b100 .
$end
#0
$dumpvars
bx @
0>
b1111 =
bx <
0:
b1111 9
bx 8
06
b1111 5
bx 4
12
b1111 1
b1 0
bx /
b100 -
bx ,
bx +
bx *
bx )
bx (
b1111 '
b0 &
1%
b1111 $
1#
b0 "
bx !
$end
#10
0#
#20
b1111 !
b1111 (
b1111 /
b1111 ,
b1111 4
1#
#25
02
16
bx !
bx (
bx /
b10 0
b101 -
b1 "
b1 &
#30
0#
#40
b1111 !
b1111 (
b1111 /
b1111 +
b1111 8
1#
#45
06
1:
bx !
bx (
bx /
b100 0
b110 -
b10 "
b10 &
#50
0#
#60
b1111 !
b1111 (
b1111 /
b1111 *
b1111 <
1#
#65
0:
1>
bx !
bx (
bx /
b1000 0
b111 -
b11 "
b11 &
#70
0#
#80
b1111 !
b1111 (
b1111 /
b1111 )
b1111 @
1#
#90
0#
#100
1#
#105
0>
b0 0
b0 $
b0 '
b0 1
b0 5
b0 9
b0 =
b0 "
b0 &
b0 -
0%
#110
0#
#120
1#
#125
b1 -
b1 "
b1 &
#130
0#
#140
1#
#145
b10 -
b10 "
b10 &
#150
0#
#160
1#
#165
b11 -
b11 "
b11 &
