Panchul/unit8/fsm22/fsm22_mealey.sv
//  Вариант 22
//  КА Мили с синхронными выходами
module      fsm22_mealey(
    //  тактирование
    input       clk,
    //  асинхронный сброс
    input       reset_n,
    //  сигнал разрешения работы
    input       enable,
    //  входной сигнал (2 битный)
    input       [1:0] a,
    //  выходной сигнал
    output      reg [1:0] y
);

//  возможные состояния
parameter       [1:0] S0 = 0, S1 = 1, S2 = 2, S3 = 3;
//  варианты входного сигнала
parameter       [1:0] A0 = 0, A1 = 1, A2 = 2, A3 = 3;
//  варианты выхода
parameter       [1:0] Y0 = 0, Y1 = 1, Y2 = 2;
//  текущее состояние
reg             [1:0] state;
//  следующее состояние
reg             [1:0] next_state;
//  шина


//  логика вычисления следующего состояния
always @(*) begin

case    (   state)
S0 : begin
    case (  a)
    A0, A1, A2 :
        next_state = S1;
    A3:
        next_state = S3;
    endcase
end
S1 : begin
    case (  a)
    A0, A1 :
        next_state = S2;
    A2 :
        next_state = S3;
    A3 :
        next_state = S0;
    endcase
end
S2 : begin
    case (  a)
    A0, A2, A3 :
        next_state = S2;
    A1 :
        next_state = S3;
    endcase
end
S3 : begin
    case (  a)
    A0 :
        next_state = S2;
    A1, A3 :
        next_state = S0;
    A2 :
        next_state = S3;
    endcase
end
default :
    next_state = S0;
endcase

end

//  регистр
always @(posedge clk or negedge reset_n) begin
    if (    !reset_n) begin
        state <= S0;
    end
    else if (   enable) begin
        state <= next_state;
    end
end

//  выходная логика - по заданию она синхронная
always @(posedge clk) begin
case (  state) 
S0 :
    case (  a) 
        A0, A1, A2 :
            y <= Y1;
        A3 :
            y <= Y0;
    endcase
S1 :
    case (  a)
        A0, A1, A2 :
            y <= Y0;
        A3 :
            y <= Y2;
    endcase
S2 :
    y <= Y0;
S3 :
    case (  a)
        A0, A2 :
            y <= Y0;
        A1, A3 :
            y <= Y2;
    endcase
endcase

end

endmodule

Panchul/unit8/fsm22/fsm22_moore.sv
//  Вариант 22
//  КА Мура с синхронными выходами
module      fsm22_moore(
    //  тактирование
    input       clk,
    //  асинхронный сброс
    input       reset_n,
    //  сигнал разрешения работы
    input       enable,
    //  входной сигнал (2 битный)
    input       [1:0] a,
    //  выходной сигнал
    output      reg [1:0] y
);

//  возможные состояния
parameter       [1:0] S0 = 0, S1 = 1, S2 = 2, S3 = 3;
//  варианты входного сигнала
parameter       [1:0] A0 = 0, A1 = 1, A2 = 2, A3 = 3;
//  варианты выхода
parameter       [1:0] Y0 = 0, Y1 = 1, Y2 = 2;
//  текущее состояние
reg             [1:0] state;
//  следующее состояние
reg             [1:0] next_state;
//  шина


//  логика вычисления следующего состояния
always @(*) begin

case    (   state)
S0 : begin
    case (  a)
    A0, A1, A2 :
        next_state = S1;
    A3:
        next_state = S3;
    endcase
end
S1 : begin
    case (  a)
    A0, A1 :
        next_state = S2;
    A2 :
        next_state = S3;
    A3 :
        next_state = S0;
    endcase
end
S2 : begin
    case (  a)
    A0, A2, A3 :
        next_state = S2;
    A1 :
        next_state = S3;
    endcase
end
S3 : begin
    case (  a)
    A0 :
        next_state = S2;
    A1, A3 :
        next_state = S0;
    A2 :
        next_state = S3;
    endcase
end
default :
    next_state = S0;
endcase

end

//  регистр
always @(posedge clk or negedge reset_n) begin
    if (    !reset_n) begin
        state <= S0;
    end
    else if (   enable) begin
        state <= next_state;
    end
end

//  выходная логика - по заданию она синхронная
always @(posedge clk) begin
//  логика пусть не имеет задержки на 1 такт
//  значит вычисление ведем от след состояния
case (  next_state) 
//  но сами условия те же
//  оценка следующего состояния делает синхронными y и state
S0 :
    y <= Y2;
S1 :
    y <= Y1;
S2 :
    y <= Y0;
S3 :
    y <= Y0;

endcase

end

endmodule

Panchul/unit8/fsm22/testbench.sv
`timescale 1ns / 1ns

module      testbench;

//  тактирование
reg         clk;
//  асинхронный сброс
reg         reset_n;
//  сигнал разрешения работы
reg         enable;
//  входной сигнал (2 битный)
reg         [1:0] a;
//  выходной сигнал
wire        [1:0] y;
wire        [1:0] y_mealey;
//  состояние
wire        [1:0] state;
wire        [1:0] state_mealey;


//  подключение устройства
fsm22_moore dut(
    .clk(clk),
    .reset_n(reset_n),
    .enable(enable),
    .a(a),
    .y(y)
);

fsm22_mealey dut2(
    .clk(clk),
    .reset_n(reset_n),
    .enable(enable),
    .a(a),
    .y(y_mealey)
);

assign state = dut.state;
assign state_mealey = dut2.state;

initial begin
    $dumpfile("wave.vcd");
    $dumpvars;
end

//  симуляция
initial begin

    //  сброс
    clk = 1;
    reset_n = 0;
    enable = 0;
    a = 2'b10;
    #40;
    //  снимаем сброс
    enable = 0;
    reset_n = 1;
    //  ждем
    #10;
    //  тест  - проход по кругу
    //  S0 -> S1 при a = 2 (один из вариантов)
    
    enable = 1;
    //  такт
    #20;
    //  S1 -> S2 при a = 0
    a = 2'b00;
    //  такт
    #20;
    //  S2 -> S2 при a = 0 - проверим
    #20;
    //  S2 -> S3 при a = 1
    a = 2'b01;
    #20;
    //  S3 -> S0 при a = 3
    a = 2'b11;
    #20;
    //  S0 -> S3 при a = 3
    #20;
    //  закрепляем состояние
    enable = 0;
    #40;
    //  конец симуляции
    $finish;

end

//  тактирование
always begin
    //  такт длится 20 у.е.
    #10;
    clk = ~clk;
end

endmodule

Panchul/unit8/fsm22/wave.vcd
$date
	Sun Sep 20 17:01:06 2026
$end
$version
	Icarus Verilog
$end
$timescale
	1ns
$end
$scope module testbench $end
$var wire 2 ! state [1:0] $end
$var wire 2 " state_mealey [1:0] $end
$var wire 2 # y_mealey [1:0] $end
$var wire 2 $ y [1:0] $end
$var reg 2 % a [1:0] $end
$var reg 1 & clk $end
$var reg 1 ' enable $end
$var reg 1 ( reset_n $end
$scope module dut $end
$var wire 2 ) a [1:0] $end
$var wire 1 & clk $end
$var wire 1 ' enable $end
$var wire 1 ( reset_n $end
$var reg 2 * next_state [1:0] $end
$var reg 2 + state [1:0] $end
$var reg 2 , y [1:0] $end
$upscope $end
$scope module dut2 $end
$var wire 2 - a [1:0] $end
$var wire 1 & clk $end
$var wire 1 ' enable $end
$var wire 1 ( reset_n $end
$var reg 2 . next_state [1:0] $end
$var reg 2 / state [1:0] $end
$var reg 2 0 y [1:0] $end
$upscope $end
$upscope $end
$enddefinitions $end
#0
$dumpvars
bx 0
b0 /
b1 .
b10 -
bx ,
b0 +
b1 *
b10 )
0(
0'
1&
b10 %
bx $
bx #
b0 "
b0 !
$end
#10
0&
#20
b1 #
b1 0
b1 $
b1 ,
1&
#30
0&
#40
1&
1(
#50
0&
1'
#60
b11 .
b11 *
b1 "
b1 /
b1 !
b1 +
1&
#70
b10 *
b10 .
0&
b0 %
b0 )
b0 -
#80
b0 $
b0 ,
b0 #
b0 0
b10 !
b10 +
b10 "
b10 /
1&
#90
0&
#100
1&
#110
b11 *
b11 .
0&
b1 %
b1 )
b1 -
#120
b0 *
b0 .
b11 !
b11 +
b11 "
b11 /
1&
#130
0&
b11 %
b11 )
b11 -
#140
b11 .
b11 *
b10 #
b10 0
b10 $
b10 ,
b0 "
b0 /
b0 !
b0 +
1&
#150
0&
#160
b0 *
b0 .
b0 $
b0 ,
b0 #
b0 0
b11 !
b11 +
b11 "
b11 /
1&
#170
0&
0'
#180
b10 #
b10 0
b10 $
b10 ,
1&
