Panchul/unit7/rom_and4/rom_and4.sv
module      rom_and4(
    input       [3:0] x,
    output      reg y
);


//  4И в виде простой ROM-таблицы
always @(*) begin
    case (x)
        4'b0000 :   y <= 0;
        4'b0001 :   y <= 0;
        4'b0010 :   y <= 0;
        4'b0011 :   y <= 0;
        4'b0100 :   y <= 0;
        4'b0101 :   y <= 0;
        4'b0110 :   y <= 0;
        4'b0111 :   y <= 0;
        4'b1000 :   y <= 0;
        4'b1001 :   y <= 0;
        4'b1010 :   y <= 0;
        4'b1011 :   y <= 0;
        4'b1100 :   y <= 0;
        4'b1101 :   y <= 0;
        4'b1110 :   y <= 0;
        4'b1111 :   y <= 1;
    endcase
end

endmodule

Panchul/unit7/rom_and4/testbench.sv
`timescale 1ns / 1ns

//  тестирование простого 4И в виде ROM-таблицы
module  testbench;

reg     [3:0] x;
wire    y;

rom_and4    dut(
    .x(x),
    .y(y)
);

initial begin
    x = 4'b0000;
    repeat (15) begin
        //  пробегаем по всем вариантам
        #10;
        x = x + 4'b0001;
    end
end

initial begin
    #160;
    $finish;
end

initial begin
    $dumpfile("wave.vcd");
    $dumpvars;
end



endmodule

Panchul/unit7/rom_and4/wave.vcd
$date
	Sun Aug 30 21:00:42 2026
$end
$version
	Icarus Verilog
$end
$timescale
	1ns
$end
$scope module testbench $end
$var wire 1 ! y $end
$var reg 4 " x [3:0] $end
$scope module dut $end
$var wire 4 # x [3:0] $end
$var reg 1 ! y $end
$upscope $end
$upscope $end
$enddefinitions $end
$comment Show the parameter values. $end
$dumpall
$end
#0
$dumpvars
b0 #
b0 "
0!
$end
#10
b1 "
b1 #
#20
b10 "
b10 #
#30
b11 "
b11 #
#40
b100 "
b100 #
#50
b101 "
b101 #
#60
b110 "
b110 #
#70
b111 "
b111 #
#80
b1000 "
b1000 #
#90
b1001 "
b1001 #
#100
b1010 "
b1010 #
#110
b1011 "
b1011 #
#120
b1100 "
b1100 #
#130
b1101 "
b1101 #
#140
b1110 "
b1110 #
#150
1!
b1111 "
b1111 #
