Panchul/unit7/ram_example/ram_parametric.sv
//  параметризованное ОЗУ
module      ram_parametric #(
    parameter   DATA_WIDTH = 4,
    parameter   ADDR_WIDTH = 6
) (
    input       [(DATA_WIDTH - 1) : 0] data_in,
    input       [(ADDR_WIDTH - 1) : 0] addr,
    input       we,
    input       clk,
    output      [(DATA_WIDTH - 1) : 0] data_out,
    output      [(ADDR_WIDTH - 1) : 0] addr_out
);

//  массив памяти 
reg     [(DATA_WIDTH - 1) : 0] ram[0 : 2**ADDR_WIDTH - 1];
//  регистр, который хранит адрес регистра, с которого в данный момент выполняется чтение
reg     [(ADDR_WIDTH - 1) : 0] addr_reg;

always @(posedge clk) begin

    if (    we) begin
        //  операция записи
        ram[addr] <= data_in;
    end

    //  обновляем регистр, который хранит текущий адрес (синхронно по тактовому сигналу)
    addr_reg <= addr;

end

//  операция чтения
assign      data_out = ram[addr_reg];
//  выводим адрес, данные с которого выдаются на выход
assign      addr_out = addr_reg;


endmodule

Panchul/unit7/ram_example/testbench.sv
`timescale 1ns / 1ns

module      testbench;

reg     [3:0] data_in;
reg     [5:0] addr;
reg     we;
reg     clk;
wire    [3:0] data_out;
wire    [5:0] addr_out;

ram_parametric #(
    .DATA_WIDTH(4),
    .ADDR_WIDTH(6)
) dut (
    .data_in(data_in),
    .addr(addr),
    .we(we),
    .clk(clk),
    .data_out(data_out),
    .addr_out(addr_out)
);

initial begin
    clk = 0;
    we = 0;
    addr = 6'b000000;
    data_in = 4'b0000;

    //  запись в память
    #20; we = 1;

    for (addr = 0; addr < 6; addr = addr + 1) begin
        #20;
        data_in = data_in + 1;
    end

    //  чтение данных из памяти
    #20; we = 0;

    for (addr = 0; addr < 6; addr = addr + 1) begin
        #20;
    end

end

//  генерация клока
always #10 clk = ~clk;

initial begin
    #300;
    $finish;
end

initial begin
    $dumpfile("wave.vcd");
    $dumpvars;
end


endmodule

Panchul/unit7/ram_example/wave.vcd
$date
	Sun Aug 30 21:57:07 2026
$end
$version
	Icarus Verilog
$end
$timescale
	1ns
$end
$scope module testbench $end
$var wire 4 ! data_out [3:0] $end
$var wire 6 " addr_out [5:0] $end
$var reg 6 # addr [5:0] $end
$var reg 1 $ clk $end
$var reg 4 % data_in [3:0] $end
$var reg 1 & we $end
$scope module dut $end
$var wire 6 ' addr [5:0] $end
$var wire 6 ( addr_out [5:0] $end
$var wire 1 $ clk $end
$var wire 4 ) data_in [3:0] $end
$var wire 4 * data_out [3:0] $end
$var wire 1 & we $end
$var parameter 32 + ADDR_WIDTH $end
$var parameter 32 , DATA_WIDTH $end
$var reg 6 - addr_reg [5:0] $end
$upscope $end
$upscope $end
$enddefinitions $end
$comment Show the parameter values. $end
$dumpall
b100 ,
b110 +
$end
#0
$dumpvars
bx -
bx *
b0 )
bx (
b0 '
0&
b0 %
0$
b0 #
bx "
bx !
$end
#10
b0 "
b0 (
b0 -
1$
#20
0$
1&
#30
b0 !
b0 *
1$
#40
0$
b1 #
b1 '
b1 %
b1 )
#50
b1 !
b1 *
b1 "
b1 (
b1 -
1$
#60
0$
b10 #
b10 '
b10 %
b10 )
#70
b10 !
b10 *
b10 "
b10 (
b10 -
1$
#80
0$
b11 #
b11 '
b11 %
b11 )
#90
b11 !
b11 *
b11 "
b11 (
b11 -
1$
#100
0$
b100 #
b100 '
b100 %
b100 )
#110
b100 !
b100 *
b100 "
b100 (
b100 -
1$
#120
0$
b101 #
b101 '
b101 %
b101 )
#130
b101 !
b101 *
b101 "
b101 (
b101 -
1$
#140
0$
b110 #
b110 '
b110 %
b110 )
#150
b110 !
b110 *
b110 "
b110 (
b110 -
1$
#160
0$
b0 #
b0 '
0&
#170
b0 !
b0 *
b0 "
b0 (
b0 -
1$
#180
0$
b1 #
b1 '
#190
b1 !
b1 *
b1 "
b1 (
b1 -
1$
#200
0$
b10 #
b10 '
#210
b10 !
b10 *
b10 "
b10 (
b10 -
1$
#220
0$
b11 #
b11 '
#230
b11 !
b11 *
b11 "
b11 (
b11 -
1$
#240
0$
b100 #
b100 '
#250
b100 !
b100 *
b100 "
b100 (
b100 -
1$
#260
0$
b101 #
b101 '
#270
b101 !
b101 *
b101 "
b101 (
b101 -
1$
#280
0$
b110 #
b110 '
#290
b110 !
b110 *
b110 "
b110 (
b110 -
1$
