Panchul/unit7/stack_with_signals/stack_with_signals.sv
//  модуль стека с использованием указателя
//  дополнительно содержит сигналы "пустой" и "полон"
module      stack_with_signals #(
    parameter   DATA_WIDTH = 8,
    parameter   PTR_WIDTH = 2
) (
    //  тактирование
    input       clk,
    //  асинхронный сигнал сброса
    input       rst_n,
    //  сигнал записи
    input       push,
    //  сигнал чтения
    input       pop,
    //  данные на запись
    input       [(DATA_WIDTH - 1) : 0] write_data,
    //  прочитанные данные
    output      reg [(DATA_WIDTH - 1) : 0] read_data,

    //  сигнал "пустой"
    output      stack_empty,
    //  сигнал "полный"
    output      stack_full
);

//  сам стек
reg             [(DATA_WIDTH - 1) : 0] stack[0 : (2**PTR_WIDTH - 1)];
//  указатель на вершину
reg             [(PTR_WIDTH - 1) : 0] pointer;

always  @(posedge clk or negedge rst_n) begin
    if (    !rst_n) begin
        //  по сбросу указатель указывает на основание
        pointer <= {PTR_WIDTH{1'b0}};
    end
    else begin
        case (  {push, pop}) 
            2'b10 : begin
                //  запись в стек
                if (    pointer < (2**PTR_WIDTH - 1)) begin
                    //  если есть куда писать
                    stack[pointer] <= write_data;
                    pointer <= pointer + 1;
                end
                else begin
                    //  указывает на вершину стека
                    //  новые данные затирают значение в верхнем регистре
                    stack[pointer] <= write_data;
                end
            end

            2'b01 : begin
                //  чтение из стека
                if (    pointer != 0) begin
                    //  если есть что читать
                    read_data <= stack[pointer - 1];
                    pointer <= pointer - 1;
                end
                else begin
                    //  указывает на основание
                    //  данных нет, выдаем 0
                    read_data <= {DATA_WIDTH{1'b0}};
                end
            end

            default : begin
                //  либо нет записи
                //  либо ошибка сигналов
                //  выдаем значение адресуемое указателем стека
                read_data <= stack[pointer];
            end
        endcase
    end
end

//  сигнал пустой
assign stack_empty = (pointer == {PTR_WIDTH{1'b0}});
//  сигнал полон
assign stack_full = (pointer == (2**PTR_WIDTH - 1));

endmodule

Panchul/unit7/stack_with_signals/testbench.sv
`timescale 1ns / 1ns

module      testbench;

//  регистры для теста
reg         clk;
reg         reset;
reg         push;
reg         pop;
reg         [7:0] write_data;
wire        [7:0] read_data;
wire        stack_empty;
wire        stack_full;

stack_with_signals #(
    .PTR_WIDTH(2),
    .DATA_WIDTH(8)
) dut (
    .clk(clk),
    .rst_n(~reset),
    .push(push),
    .pop(pop),
    .write_data(write_data),
    .read_data(read_data),
    .stack_empty(stack_empty),
    .stack_full(stack_full)
);

initial begin
    $dumpfile("wave.vcd");
    $dumpvars;
end

initial begin
    //  начальные значения
    clk = 1;
    reset = 1;
    push = 1;
    pop = 0;
    write_data = 8'b00000000;

    //  запись
    #20;    write_data = 8'b00000001;
    #10;    reset = 0;
    #10;    write_data = 8'b00000010;
    #20;    write_data = 8'b00000011;
    #20;    write_data = 8'b00000100;
    #20;    write_data = 8'b00000101;
    #20;    write_data = 8'b00000110;
    push = 0;
    pop = 1;
    #20;    write_data = 8'b00000111;
    #20;    write_data = 8'b00001000;
    #20;    write_data = 8'b00001001;
    #20;    write_data = 8'b00001011;

end

//  тактирование
always  #10 clk = ~clk;

//  окончание
initial begin
    #220;
    $finish;
end

endmodule

Panchul/unit7/stack_with_signals/wave.vcd
$date
	Sun Sep 13 12:29:47 2026
$end
$version
	Icarus Verilog
$end
$timescale
	1ns
$end
$scope module testbench $end
$var wire 1 ! stack_full $end
$var wire 1 " stack_empty $end
$var wire 8 # read_data [7:0] $end
$var reg 1 $ clk $end
$var reg 1 % pop $end
$var reg 1 & push $end
$var reg 1 ' reset $end
$var reg 8 ( write_data [7:0] $end
$scope module dut $end
$var wire 1 $ clk $end
$var wire 1 % pop $end
$var wire 1 & push $end
$var wire 1 ) rst_n $end
$var wire 8 * write_data [7:0] $end
$var wire 1 ! stack_full $end
$var wire 1 " stack_empty $end
$var reg 2 + pointer [1:0] $end
$var reg 8 , read_data [7:0] $end
$upscope $end
$upscope $end
$enddefinitions $end
#0
$dumpvars
bx ,
b0 +
b0 *
0)
b0 (
1'
1&
0%
1$
bx #
1"
0!
$end
#10
0$
#20
1$
b1 (
b1 *
#30
1)
0$
0'
#40
0"
b1 +
1$
b10 (
b10 *
#50
0$
#60
b10 +
1$
b11 (
b11 *
#70
0$
#80
1!
b11 +
1$
b100 (
b100 *
#90
0$
#100
1$
b101 (
b101 *
#110
0$
#120
0!
b10 +
b100 #
b100 ,
1$
1%
0&
b110 (
b110 *
#130
0$
#140
b1 +
b11 #
b11 ,
1$
b111 (
b111 *
#150
0$
#160
1"
b0 +
b10 #
b10 ,
1$
b1000 (
b1000 *
#170
0$
#180
b0 #
b0 ,
1$
b1001 (
b1001 *
#190
0$
#200
1$
b1011 (
b1011 *
