Panchul/unit7/rom_sinx/rom_sinx.sv
//  ROM-память для генерации синуса
module      rom_sinx #(
    parameter       X_WIDTH = 10,
    parameter       Y_WIDTH = 8
) (
    input       [(X_WIDTH - 1) : 0] x,
    input       clk,
    output      [(Y_WIDTH - 1) : 0] y
);

localparam real PI = 3.141592653589793;

//  сама память
reg         [(Y_WIDTH - 1) : 0] rom_data[(2**X_WIDTH - 1):0];
//  регистр для хранения адреса чтения
reg         [(X_WIDTH - 1) : 0] addr_reg;

integer     i;
integer     arg;

initial begin
    for (   i = 0; i <= (2**X_WIDTH - 1) ; i = i + 1) begin
        arg = $rtoi($sin(2.0 * PI * i / $itor(2**X_WIDTH))  *  $itor(2**(Y_WIDTH - 1) - 1));
        rom_data[i] = arg[(Y_WIDTH - 1) : 0];
    end
end

//  выдача выхода
always  @(posedge clk) begin
    addr_reg <= x;
end

assign  y = rom_data[addr_reg];

endmodule

Panchul/unit7/rom_sinx/testbench.sv
`timescale 1ns / 1ps

module      testbench;

reg         [9:0] x;
reg         clk;
wire        [7:0] y;
integer     i;

rom_sinx #(
    .X_WIDTH(10),
    .Y_WIDTH(8)
) dut (
    .x(x),
    .clk(clk),
    .y(y)
);

initial begin
    $dumpfile("wave.vcd");
    $dumpvars;
end

initial begin
    clk = 1;
    x = 0;
    #5;
    for (   i = 0 ; i < (2**10 - 1); i = i + 1) begin
        #20;
        if (    (i % 10) == 0) begin
            $display("i = %d\n", i);
        end
        x = x + 1;
    end

    $finish;


end

//  тактирование
always begin
    #10;
    clk = ~clk;
end

endmodule

Panchul/unit7/rom_sinx/wave.vcd
$date
	Sat Sep 12 20:17:18 2026
$end
$version
	Icarus Verilog
$end
$timescale
	1ps
$end
$scope module testbench $end
$var wire 8 ! y [7:0] $end
$var reg 1 " clk $end
$var reg 10 # x [9:0] $end
$var integer 32 $ i [31:0] $end
$scope module dut $end
$var wire 1 " clk $end
$var wire 10 % x [9:0] $end
$var wire 8 & y [7:0] $end
$var reg 10 ' addr_reg [9:0] $end
$var integer 32 ( arg [31:0] $end
$var integer 32 ) i [31:0] $end
$upscope $end
$upscope $end
$enddefinitions $end
#0
$dumpvars
b10000000000 )
b0 (
b0 '
b0 &
b0 %
bx $
b0 #
1"
b0 !
$end
#5000
b0 $
#10000
0"
#20000
1"
#25000
b1 $
b1 #
b1 %
#30000
0"
#40000
b1 '
1"
#45000
b10 $
b10 #
b10 %
#50000
0"
#60000
b1 !
b1 &
b10 '
1"
#65000
b11 $
b11 #
b11 %
#70000
0"
#80000
b10 !
b10 &
b11 '
1"
#85000
b100 $
b100 #
b100 %
#90000
0"
#100000
b11 !
b11 &
b100 '
1"
#105000
b101 $
b101 #
b101 %
#110000
0"
#120000
b101 '
1"
#125000
b110 $
b110 #
b110 %
#130000
0"
#140000
b100 !
b100 &
b110 '
1"
#145000
b111 $
b111 #
b111 %
#150000
0"
#160000
b101 !
b101 &
b111 '
1"
#165000
b1000 $
b1000 #
b1000 %
#170000
0"
#180000
b110 !
b110 &
b1000 '
1"
#185000
b1001 $
b1001 #
b1001 %
#190000
0"
#200000
b111 !
b111 &
b1001 '
1"
#205000
b1010 $
b1010 #
b1010 %
#210000
0"
#220000
b1010 '
1"
#225000
b1011 $
b1011 #
b1011 %
#230000
0"
#240000
b1000 !
b1000 &
b1011 '
1"
#245000
b1100 $
b1100 #
b1100 %
#250000
0"
#260000
b1001 !
b1001 &
b1100 '
1"
#265000
b1101 $
b1101 #
b1101 %
#270000
0"
#280000
b1010 !
b1010 &
b1101 '
1"
#285000
b1110 $
b1110 #
b1110 %
#290000
0"
#300000
b1110 '
1"
#305000
b1111 $
b1111 #
b1111 %
#310000
0"
#320000
b1011 !
b1011 &
b1111 '
1"
#325000
b10000 $
b10000 #
b10000 %
#330000
0"
#340000
b1100 !
b1100 &
b10000 '
1"
#345000
b10001 $
b10001 #
b10001 %
#350000
0"
#360000
b1101 !
b1101 &
b10001 '
1"
#365000
b10010 $
b10010 #
b10010 %
#370000
0"
#380000
b10010 '
1"
#385000
b10011 $
b10011 #
b10011 %
#390000
0"
#400000
b1110 !
b1110 &
b10011 '
1"
#405000
b10100 $
b10100 #
b10100 %
#410000
0"
#420000
b1111 !
b1111 &
b10100 '
1"
#425000
b10101 $
b10101 #
b10101 %
#430000
0"
#440000
b10000 !
b10000 &
b10101 '
1"
#445000
b10110 $
b10110 #
b10110 %
#450000
0"
#460000
b10001 !
b10001 &
b10110 '
1"
#465000
b10111 $
b10111 #
b10111 %
#470000
0"
#480000
b10111 '
1"
#485000
b11000 $
b11000 #
b11000 %
#490000
0"
#500000
b10010 !
b10010 &
b11000 '
1"
#505000
b11001 $
b11001 #
b11001 %
#510000
0"
#520000
b10011 !
b10011 &
b11001 '
1"
#525000
b11010 $
b11010 #
b11010 %
#530000
0"
#540000
b10100 !
b10100 &
b11010 '
1"
#545000
b11011 $
b11011 #
b11011 %
#550000
0"
#560000
b11011 '
1"
#565000
b11100 $
b11100 #
b11100 %
#570000
0"
#580000
b10101 !
b10101 &
b11100 '
1"
#585000
b11101 $
b11101 #
b11101 %
#590000
0"
#600000
b10110 !
b10110 &
b11101 '
1"
#605000
b11110 $
b11110 #
b11110 %
#610000
0"
#620000
b10111 !
b10111 &
b11110 '
1"
#625000
b11111 $
b11111 #
b11111 %
#630000
0"
#640000
b11000 !
b11000 &
b11111 '
1"
#645000
b100000 $
b100000 #
b100000 %
#650000
0"
#660000
b100000 '
1"
#665000
b100001 $
b100001 #
b100001 %
#670000
0"
#680000
b11001 !
b11001 &
b100001 '
1"
#685000
b100010 $
b100010 #
b100010 %
#690000
0"
#700000
b11010 !
b11010 &
b100010 '
1"
#705000
b100011 $
b100011 #
b100011 %
#710000
0"
#720000
b11011 !
b11011 &
b100011 '
1"
#725000
b100100 $
b100100 #
b100100 %
#730000
0"
#740000
b100100 '
1"
#745000
b100101 $
b100101 #
b100101 %
#750000
0"
#760000
b11100 !
b11100 &
b100101 '
1"
#765000
b100110 $
b100110 #
b100110 %
#770000
0"
#780000
b11101 !
b11101 &
b100110 '
1"
#785000
b100111 $
b100111 #
b100111 %
#790000
0"
#800000
b11110 !
b11110 &
b100111 '
1"
#805000
b101000 $
b101000 #
b101000 %
#810000
0"
#820000
b101000 '
1"
#825000
b101001 $
b101001 #
b101001 %
#830000
0"
#840000
b11111 !
b11111 &
b101001 '
1"
#845000
b101010 $
b101010 #
b101010 %
#850000
0"
#860000
b100000 !
b100000 &
b101010 '
1"
#865000
b101011 $
b101011 #
b101011 %
#870000
0"
#880000
b100001 !
b100001 &
b101011 '
1"
#885000
b101100 $
b101100 #
b101100 %
#890000
0"
#900000
b101100 '
1"
#905000
b101101 $
b101101 #
b101101 %
#910000
0"
#920000
b100010 !
b100010 &
b101101 '
1"
#925000
b101110 $
b101110 #
b101110 %
#930000
0"
#940000
b100011 !
b100011 &
b101110 '
1"
#945000
b101111 $
b101111 #
b101111 %
#950000
0"
#960000
b100100 !
b100100 &
b101111 '
1"
#965000
b110000 $
b110000 #
b110000 %
#970000
0"
#980000
b110000 '
1"
#985000
b110001 $
b110001 #
b110001 %
#990000
0"
#1000000
b100101 !
b100101 &
b110001 '
1"
#1005000
b110010 $
b110010 #
b110010 %
#1010000
0"
#1020000
b100110 !
b100110 &
b110010 '
1"
#1025000
b110011 $
b110011 #
b110011 %
#1030000
0"
#1040000
b100111 !
b100111 &
b110011 '
1"
#1045000
b110100 $
b110100 #
b110100 %
#1050000
0"
#1060000
b110100 '
1"
#1065000
b110101 $
b110101 #
b110101 %
#1070000
0"
#1080000
b101000 !
b101000 &
b110101 '
1"
#1085000
b110110 $
b110110 #
b110110 %
#1090000
0"
#1100000
b101001 !
b101001 &
b110110 '
1"
#1105000
b110111 $
b110111 #
b110111 %
#1110000
0"
#1120000
b101010 !
b101010 &
b110111 '
1"
#1125000
b111000 $
b111000 #
b111000 %
#1130000
0"
#1140000
b111000 '
1"
#1145000
b111001 $
b111001 #
b111001 %
#1150000
0"
#1160000
b101011 !
b101011 &
b111001 '
1"
#1165000
b111010 $
b111010 #
b111010 %
#1170000
0"
#1180000
b101100 !
b101100 &
b111010 '
1"
#1185000
b111011 $
b111011 #
b111011 %
#1190000
0"
#1200000
b111011 '
1"
#1205000
b111100 $
b111100 #
b111100 %
#1210000
0"
#1220000
b101101 !
b101101 &
b111100 '
1"
#1225000
b111101 $
b111101 #
b111101 %
#1230000
0"
#1240000
b101110 !
b101110 &
b111101 '
1"
#1245000
b111110 $
b111110 #
b111110 %
#1250000
0"
#1260000
b101111 !
b101111 &
b111110 '
1"
#1265000
b111111 $
b111111 #
b111111 %
#1270000
0"
#1280000
b111111 '
1"
#1285000
b1000000 $
b1000000 #
b1000000 %
#1290000
0"
#1300000
b110000 !
b110000 &
b1000000 '
1"
#1305000
b1000001 $
b1000001 #
b1000001 %
#1310000
0"
#1320000
b110001 !
b110001 &
b1000001 '
1"
#1325000
b1000010 $
b1000010 #
b1000010 %
#1330000
0"
#1340000
b110010 !
b110010 &
b1000010 '
1"
#1345000
b1000011 $
b1000011 #
b1000011 %
#1350000
0"
#1360000
b1000011 '
1"
#1365000
b1000100 $
b1000100 #
b1000100 %
#1370000
0"
#1380000
b110011 !
b110011 &
b1000100 '
1"
#1385000
b1000101 $
b1000101 #
b1000101 %
#1390000
0"
#1400000
b110100 !
b110100 &
b1000101 '
1"
#1405000
b1000110 $
b1000110 #
b1000110 %
#1410000
0"
#1420000
b1000110 '
1"
#1425000
b1000111 $
b1000111 #
b1000111 %
#1430000
0"
#1440000
b110101 !
b110101 &
b1000111 '
1"
#1445000
b1001000 $
b1001000 #
b1001000 %
#1450000
0"
#1460000
b110110 !
b110110 &
b1001000 '
1"
#1465000
b1001001 $
b1001001 #
b1001001 %
#1470000
0"
#1480000
b110111 !
b110111 &
b1001001 '
1"
#1485000
b1001010 $
b1001010 #
b1001010 %
#1490000
0"
#1500000
b1001010 '
1"
#1505000
b1001011 $
b1001011 #
b1001011 %
#1510000
0"
#1520000
b111000 !
b111000 &
b1001011 '
1"
#1525000
b1001100 $
b1001100 #
b1001100 %
#1530000
0"
#1540000
b111001 !
b111001 &
b1001100 '
1"
#1545000
b1001101 $
b1001101 #
b1001101 %
#1550000
0"
#1560000
b1001101 '
1"
#1565000
b1001110 $
b1001110 #
b1001110 %
#1570000
0"
#1580000
b111010 !
b111010 &
b1001110 '
1"
#1585000
b1001111 $
b1001111 #
b1001111 %
#1590000
0"
#1600000
b111011 !
b111011 &
b1001111 '
1"
#1605000
b1010000 $
b1010000 #
b1010000 %
#1610000
0"
#1620000
b1010000 '
1"
#1625000
b1010001 $
b1010001 #
b1010001 %
#1630000
0"
#1640000
b111100 !
b111100 &
b1010001 '
1"
#1645000
b1010010 $
b1010010 #
b1010010 %
#1650000
0"
#1660000
b111101 !
b111101 &
b1010010 '
1"
#1665000
b1010011 $
b1010011 #
b1010011 %
#1670000
0"
#1680000
b1010011 '
1"
#1685000
b1010100 $
b1010100 #
b1010100 %
#1690000
0"
#1700000
b111110 !
b111110 &
b1010100 '
1"
#1705000
b1010101 $
b1010101 #
b1010101 %
#1710000
0"
#1720000
b111111 !
b111111 &
b1010101 '
1"
#1725000
b1010110 $
b1010110 #
b1010110 %
#1730000
0"
#1740000
b1010110 '
1"
#1745000
b1010111 $
b1010111 #
b1010111 %
#1750000
0"
#1760000
b1000000 !
b1000000 &
b1010111 '
1"
#1765000
b1011000 $
b1011000 #
b1011000 %
#1770000
0"
#1780000
b1000001 !
b1000001 &
b1011000 '
1"
#1785000
b1011001 $
b1011001 #
b1011001 %
#1790000
0"
#1800000
b1011001 '
1"
#1805000
b1011010 $
b1011010 #
b1011010 %
#1810000
0"
#1820000
b1000010 !
b1000010 &
b1011010 '
1"
#1825000
b1011011 $
b1011011 #
b1011011 %
#1830000
0"
#1840000
b1000011 !
b1000011 &
b1011011 '
1"
#1845000
b1011100 $
b1011100 #
b1011100 %
#1850000
0"
#1860000
b1011100 '
1"
#1865000
b1011101 $
b1011101 #
b1011101 %
#1870000
0"
#1880000
b1000100 !
b1000100 &
b1011101 '
1"
#1885000
b1011110 $
b1011110 #
b1011110 %
#1890000
0"
#1900000
b1000101 !
b1000101 &
b1011110 '
1"
#1905000
b1011111 $
b1011111 #
b1011111 %
#1910000
0"
#1920000
b1011111 '
1"
#1925000
b1100000 $
b1100000 #
b1100000 %
#1930000
0"
#1940000
b1000110 !
b1000110 &
b1100000 '
1"
#1945000
b1100001 $
b1100001 #
b1100001 %
#1950000
0"
#1960000
b1000111 !
b1000111 &
b1100001 '
1"
#1965000
b1100010 $
b1100010 #
b1100010 %
#1970000
0"
#1980000
b1100010 '
1"
#1985000
b1100011 $
b1100011 #
b1100011 %
#1990000
0"
#2000000
b1001000 !
b1001000 &
b1100011 '
1"
#2005000
b1100100 $
b1100100 #
b1100100 %
#2010000
0"
#2020000
b1001001 !
b1001001 &
b1100100 '
1"
#2025000
b1100101 $
b1100101 #
b1100101 %
#2030000
0"
#2040000
b1100101 '
1"
#2045000
b1100110 $
b1100110 #
b1100110 %
#2050000
0"
#2060000
b1001010 !
b1001010 &
b1100110 '
1"
#2065000
b1100111 $
b1100111 #
b1100111 %
#2070000
0"
#2080000
b1001011 !
b1001011 &
b1100111 '
1"
#2085000
b1101000 $
b1101000 #
b1101000 %
#2090000
0"
#2100000
b1101000 '
1"
#2105000
b1101001 $
b1101001 #
b1101001 %
#2110000
0"
#2120000
b1001100 !
b1001100 &
b1101001 '
1"
#2125000
b1101010 $
b1101010 #
b1101010 %
#2130000
0"
#2140000
b1101010 '
1"
#2145000
b1101011 $
b1101011 #
b1101011 %
#2150000
0"
#2160000
b1001101 !
b1001101 &
b1101011 '
1"
#2165000
b1101100 $
b1101100 #
b1101100 %
#2170000
0"
#2180000
b1001110 !
b1001110 &
b1101100 '
1"
#2185000
b1101101 $
b1101101 #
b1101101 %
#2190000
0"
#2200000
b1101101 '
1"
#2205000
b1101110 $
b1101110 #
b1101110 %
#2210000
0"
#2220000
b1001111 !
b1001111 &
b1101110 '
1"
#2225000
b1101111 $
b1101111 #
b1101111 %
#2230000
0"
#2240000
b1101111 '
1"
#2245000
b1110000 $
b1110000 #
b1110000 %
#2250000
0"
#2260000
b1010000 !
b1010000 &
b1110000 '
1"
#2265000
b1110001 $
b1110001 #
b1110001 %
#2270000
0"
#2280000
b1010001 !
b1010001 &
b1110001 '
1"
#2285000
b1110010 $
b1110010 #
b1110010 %
#2290000
0"
#2300000
b1110010 '
1"
#2305000
b1110011 $
b1110011 #
b1110011 %
#2310000
0"
#2320000
b1010010 !
b1010010 &
b1110011 '
1"
#2325000
b1110100 $
b1110100 #
b1110100 %
#2330000
0"
#2340000
b1110100 '
1"
#2345000
b1110101 $
b1110101 #
b1110101 %
#2350000
0"
#2360000
b1010011 !
b1010011 &
b1110101 '
1"
#2365000
b1110110 $
b1110110 #
b1110110 %
#2370000
0"
#2380000
b1010100 !
b1010100 &
b1110110 '
1"
#2385000
b1110111 $
b1110111 #
b1110111 %
#2390000
0"
#2400000
b1110111 '
1"
#2405000
b1111000 $
b1111000 #
b1111000 %
#2410000
0"
#2420000
b1010101 !
b1010101 &
b1111000 '
1"
#2425000
b1111001 $
b1111001 #
b1111001 %
#2430000
0"
#2440000
b1111001 '
1"
#2445000
b1111010 $
b1111010 #
b1111010 %
#2450000
0"
#2460000
b1010110 !
b1010110 &
b1111010 '
1"
#2465000
b1111011 $
b1111011 #
b1111011 %
#2470000
0"
#2480000
b1010111 !
b1010111 &
b1111011 '
1"
#2485000
b1111100 $
b1111100 #
b1111100 %
#2490000
0"
#2500000
b1111100 '
1"
#2505000
b1111101 $
b1111101 #
b1111101 %
#2510000
0"
#2520000
b1011000 !
b1011000 &
b1111101 '
1"
#2525000
b1111110 $
b1111110 #
b1111110 %
#2530000
0"
#2540000
b1111110 '
1"
#2545000
b1111111 $
b1111111 #
b1111111 %
#2550000
0"
#2560000
b1011001 !
b1011001 &
b1111111 '
1"
#2565000
b10000000 $
b10000000 #
b10000000 %
#2570000
0"
#2580000
b10000000 '
1"
#2585000
b10000001 $
b10000001 #
b10000001 %
#2590000
0"
#2600000
b1011010 !
b1011010 &
b10000001 '
1"
#2605000
b10000010 $
b10000010 #
b10000010 %
#2610000
0"
#2620000
b10000010 '
1"
#2625000
b10000011 $
b10000011 #
b10000011 %
#2630000
0"
#2640000
b1011011 !
b1011011 &
b10000011 '
1"
#2645000
b10000100 $
b10000100 #
b10000100 %
#2650000
0"
#2660000
b10000100 '
1"
#2665000
b10000101 $
b10000101 #
b10000101 %
#2670000
0"
#2680000
b1011100 !
b1011100 &
b10000101 '
1"
#2685000
b10000110 $
b10000110 #
b10000110 %
#2690000
0"
#2700000
b1011101 !
b1011101 &
b10000110 '
1"
#2705000
b10000111 $
b10000111 #
b10000111 %
#2710000
0"
#2720000
b10000111 '
1"
#2725000
b10001000 $
b10001000 #
b10001000 %
#2730000
0"
#2740000
b1011110 !
b1011110 &
b10001000 '
1"
#2745000
b10001001 $
b10001001 #
b10001001 %
#2750000
0"
#2760000
b10001001 '
1"
#2765000
b10001010 $
b10001010 #
b10001010 %
#2770000
0"
#2780000
b1011111 !
b1011111 &
b10001010 '
1"
#2785000
b10001011 $
b10001011 #
b10001011 %
#2790000
0"
#2800000
b10001011 '
1"
#2805000
b10001100 $
b10001100 #
b10001100 %
#2810000
0"
#2820000
b1100000 !
b1100000 &
b10001100 '
1"
#2825000
b10001101 $
b10001101 #
b10001101 %
#2830000
0"
#2840000
b10001101 '
1"
#2845000
b10001110 $
b10001110 #
b10001110 %
#2850000
0"
#2860000
b1100001 !
b1100001 &
b10001110 '
1"
#2865000
b10001111 $
b10001111 #
b10001111 %
#2870000
0"
#2880000
b10001111 '
1"
#2885000
b10010000 $
b10010000 #
b10010000 %
#2890000
0"
#2900000
b1100010 !
b1100010 &
b10010000 '
1"
#2905000
b10010001 $
b10010001 #
b10010001 %
#2910000
0"
#2920000
b10010001 '
1"
#2925000
b10010010 $
b10010010 #
b10010010 %
#2930000
0"
#2940000
b1100011 !
b1100011 &
b10010010 '
1"
#2945000
b10010011 $
b10010011 #
b10010011 %
#2950000
0"
#2960000
b10010011 '
1"
#2965000
b10010100 $
b10010100 #
b10010100 %
#2970000
0"
#2980000
b1100100 !
b1100100 &
b10010100 '
1"
#2985000
b10010101 $
b10010101 #
b10010101 %
#2990000
0"
#3000000
b10010101 '
1"
#3005000
b10010110 $
b10010110 #
b10010110 %
#3010000
0"
#3020000
b1100101 !
b1100101 &
b10010110 '
1"
#3025000
b10010111 $
b10010111 #
b10010111 %
#3030000
0"
#3040000
b10010111 '
1"
#3045000
b10011000 $
b10011000 #
b10011000 %
#3050000
0"
#3060000
b1100110 !
b1100110 &
b10011000 '
1"
#3065000
b10011001 $
b10011001 #
b10011001 %
#3070000
0"
#3080000
b10011001 '
1"
#3085000
b10011010 $
b10011010 #
b10011010 %
#3090000
0"
#3100000
b10011010 '
1"
#3105000
b10011011 $
b10011011 #
b10011011 %
#3110000
0"
#3120000
b1100111 !
b1100111 &
b10011011 '
1"
#3125000
b10011100 $
b10011100 #
b10011100 %
#3130000
0"
#3140000
b10011100 '
1"
#3145000
b10011101 $
b10011101 #
b10011101 %
#3150000
0"
#3160000
b1101000 !
b1101000 &
b10011101 '
1"
#3165000
b10011110 $
b10011110 #
b10011110 %
#3170000
0"
#3180000
b10011110 '
1"
#3185000
b10011111 $
b10011111 #
b10011111 %
#3190000
0"
#3200000
b1101001 !
b1101001 &
b10011111 '
1"
#3205000
b10100000 $
b10100000 #
b10100000 %
#3210000
0"
#3220000
b10100000 '
1"
#3225000
b10100001 $
b10100001 #
b10100001 %
#3230000
0"
#3240000
b1101010 !
b1101010 &
b10100001 '
1"
#3245000
b10100010 $
b10100010 #
b10100010 %
#3250000
0"
#3260000
b10100010 '
1"
#3265000
b10100011 $
b10100011 #
b10100011 %
#3270000
0"
#3280000
b10100011 '
1"
#3285000
b10100100 $
b10100100 #
b10100100 %
#3290000
0"
#3300000
b1101011 !
b1101011 &
b10100100 '
1"
#3305000
b10100101 $
b10100101 #
b10100101 %
#3310000
0"
#3320000
b10100101 '
1"
#3325000
b10100110 $
b10100110 #
b10100110 %
#3330000
0"
#3340000
b1101100 !
b1101100 &
b10100110 '
1"
#3345000
b10100111 $
b10100111 #
b10100111 %
#3350000
0"
#3360000
b10100111 '
1"
#3365000
b10101000 $
b10101000 #
b10101000 %
#3370000
0"
#3380000
b10101000 '
1"
#3385000
b10101001 $
b10101001 #
b10101001 %
#3390000
0"
#3400000
b1101101 !
b1101101 &
b10101001 '
1"
#3405000
b10101010 $
b10101010 #
b10101010 %
#3410000
0"
#3420000
b10101010 '
1"
#3425000
b10101011 $
b10101011 #
b10101011 %
#3430000
0"
#3440000
b1101110 !
b1101110 &
b10101011 '
1"
#3445000
b10101100 $
b10101100 #
b10101100 %
#3450000
0"
#3460000
b10101100 '
1"
#3465000
b10101101 $
b10101101 #
b10101101 %
#3470000
0"
#3480000
b10101101 '
1"
#3485000
b10101110 $
b10101110 #
b10101110 %
#3490000
0"
#3500000
b1101111 !
b1101111 &
b10101110 '
1"
#3505000
b10101111 $
b10101111 #
b10101111 %
#3510000
0"
#3520000
b10101111 '
1"
#3525000
b10110000 $
b10110000 #
b10110000 %
#3530000
0"
#3540000
b1110000 !
b1110000 &
b10110000 '
1"
#3545000
b10110001 $
b10110001 #
b10110001 %
#3550000
0"
#3560000
b10110001 '
1"
#3565000
b10110010 $
b10110010 #
b10110010 %
#3570000
0"
#3580000
b10110010 '
1"
#3585000
b10110011 $
b10110011 #
b10110011 %
#3590000
0"
#3600000
b1110001 !
b1110001 &
b10110011 '
1"
#3605000
b10110100 $
b10110100 #
b10110100 %
#3610000
0"
#3620000
b10110100 '
1"
#3625000
b10110101 $
b10110101 #
b10110101 %
#3630000
0"
#3640000
b10110101 '
1"
#3645000
b10110110 $
b10110110 #
b10110110 %
#3650000
0"
#3660000
b1110010 !
b1110010 &
b10110110 '
1"
#3665000
b10110111 $
b10110111 #
b10110111 %
#3670000
0"
#3680000
b10110111 '
1"
#3685000
b10111000 $
b10111000 #
b10111000 %
#3690000
0"
#3700000
b10111000 '
1"
#3705000
b10111001 $
b10111001 #
b10111001 %
#3710000
0"
#3720000
b1110011 !
b1110011 &
b10111001 '
1"
#3725000
b10111010 $
b10111010 #
b10111010 %
#3730000
0"
#3740000
b10111010 '
1"
#3745000
b10111011 $
b10111011 #
b10111011 %
#3750000
0"
#3760000
b10111011 '
1"
#3765000
b10111100 $
b10111100 #
b10111100 %
#3770000
0"
#3780000
b1110100 !
b1110100 &
b10111100 '
1"
#3785000
b10111101 $
b10111101 #
b10111101 %
#3790000
0"
#3800000
b10111101 '
1"
#3805000
b10111110 $
b10111110 #
b10111110 %
#3810000
0"
#3820000
b10111110 '
1"
#3825000
b10111111 $
b10111111 #
b10111111 %
#3830000
0"
#3840000
b1110101 !
b1110101 &
b10111111 '
1"
#3845000
b11000000 $
b11000000 #
b11000000 %
#3850000
0"
#3860000
b11000000 '
1"
#3865000
b11000001 $
b11000001 #
b11000001 %
#3870000
0"
#3880000
b11000001 '
1"
#3885000
b11000010 $
b11000010 #
b11000010 %
#3890000
0"
#3900000
b11000010 '
1"
#3905000
b11000011 $
b11000011 #
b11000011 %
#3910000
0"
#3920000
b1110110 !
b1110110 &
b11000011 '
1"
#3925000
b11000100 $
b11000100 #
b11000100 %
#3930000
0"
#3940000
b11000100 '
1"
#3945000
b11000101 $
b11000101 #
b11000101 %
#3950000
0"
#3960000
b11000101 '
1"
#3965000
b11000110 $
b11000110 #
b11000110 %
#3970000
0"
#3980000
b1110111 !
b1110111 &
b11000110 '
1"
#3985000
b11000111 $
b11000111 #
b11000111 %
#3990000
0"
#4000000
b11000111 '
1"
#4005000
b11001000 $
b11001000 #
b11001000 %
#4010000
0"
#4020000
b11001000 '
1"
#4025000
b11001001 $
b11001001 #
b11001001 %
#4030000
0"
#4040000
b11001001 '
1"
#4045000
b11001010 $
b11001010 #
b11001010 %
#4050000
0"
#4060000
b1111000 !
b1111000 &
b11001010 '
1"
#4065000
b11001011 $
b11001011 #
b11001011 %
#4070000
0"
#4080000
b11001011 '
1"
#4085000
b11001100 $
b11001100 #
b11001100 %
#4090000
0"
#4100000
b11001100 '
1"
#4105000
b11001101 $
b11001101 #
b11001101 %
#4110000
0"
#4120000
b11001101 '
1"
#4125000
b11001110 $
b11001110 #
b11001110 %
#4130000
0"
#4140000
b1111001 !
b1111001 &
b11001110 '
1"
#4145000
b11001111 $
b11001111 #
b11001111 %
#4150000
0"
#4160000
b11001111 '
1"
#4165000
b11010000 $
b11010000 #
b11010000 %
#4170000
0"
#4180000
b11010000 '
1"
#4185000
b11010001 $
b11010001 #
b11010001 %
#4190000
0"
#4200000
b11010001 '
1"
#4205000
b11010010 $
b11010010 #
b11010010 %
#4210000
0"
#4220000
b11010010 '
1"
#4225000
b11010011 $
b11010011 #
b11010011 %
#4230000
0"
#4240000
b1111010 !
b1111010 &
b11010011 '
1"
#4245000
b11010100 $
b11010100 #
b11010100 %
#4250000
0"
#4260000
b11010100 '
1"
#4265000
b11010101 $
b11010101 #
b11010101 %
#4270000
0"
#4280000
b11010101 '
1"
#4285000
b11010110 $
b11010110 #
b11010110 %
#4290000
0"
#4300000
b11010110 '
1"
#4305000
b11010111 $
b11010111 #
b11010111 %
#4310000
0"
#4320000
b1111011 !
b1111011 &
b11010111 '
1"
#4325000
b11011000 $
b11011000 #
b11011000 %
#4330000
0"
#4340000
b11011000 '
1"
#4345000
b11011001 $
b11011001 #
b11011001 %
#4350000
0"
#4360000
b11011001 '
1"
#4365000
b11011010 $
b11011010 #
b11011010 %
#4370000
0"
#4380000
b11011010 '
1"
#4385000
b11011011 $
b11011011 #
b11011011 %
#4390000
0"
#4400000
b11011011 '
1"
#4405000
b11011100 $
b11011100 #
b11011100 %
#4410000
0"
#4420000
b11011100 '
1"
#4425000
b11011101 $
b11011101 #
b11011101 %
#4430000
0"
#4440000
b1111100 !
b1111100 &
b11011101 '
1"
#4445000
b11011110 $
b11011110 #
b11011110 %
#4450000
0"
#4460000
b11011110 '
1"
#4465000
b11011111 $
b11011111 #
b11011111 %
#4470000
0"
#4480000
b11011111 '
1"
#4485000
b11100000 $
b11100000 #
b11100000 %
#4490000
0"
#4500000
b11100000 '
1"
#4505000
b11100001 $
b11100001 #
b11100001 %
#4510000
0"
#4520000
b11100001 '
1"
#4525000
b11100010 $
b11100010 #
b11100010 %
#4530000
0"
#4540000
b11100010 '
1"
#4545000
b11100011 $
b11100011 #
b11100011 %
#4550000
0"
#4560000
b11100011 '
1"
#4565000
b11100100 $
b11100100 #
b11100100 %
#4570000
0"
#4580000
b1111101 !
b1111101 &
b11100100 '
1"
#4585000
b11100101 $
b11100101 #
b11100101 %
#4590000
0"
#4600000
b11100101 '
1"
#4605000
b11100110 $
b11100110 #
b11100110 %
#4610000
0"
#4620000
b11100110 '
1"
#4625000
b11100111 $
b11100111 #
b11100111 %
#4630000
0"
#4640000
b11100111 '
1"
#4645000
b11101000 $
b11101000 #
b11101000 %
#4650000
0"
#4660000
b11101000 '
1"
#4665000
b11101001 $
b11101001 #
b11101001 %
#4670000
0"
#4680000
b11101001 '
1"
#4685000
b11101010 $
b11101010 #
b11101010 %
#4690000
0"
#4700000
b11101010 '
1"
#4705000
b11101011 $
b11101011 #
b11101011 %
#4710000
0"
#4720000
b11101011 '
1"
#4725000
b11101100 $
b11101100 #
b11101100 %
#4730000
0"
#4740000
b1111110 !
b1111110 &
b11101100 '
1"
#4745000
b11101101 $
b11101101 #
b11101101 %
#4750000
0"
#4760000
b11101101 '
1"
#4765000
b11101110 $
b11101110 #
b11101110 %
#4770000
0"
#4780000
b11101110 '
1"
#4785000
b11101111 $
b11101111 #
b11101111 %
#4790000
0"
#4800000
b11101111 '
1"
#4805000
b11110000 $
b11110000 #
b11110000 %
#4810000
0"
#4820000
b11110000 '
1"
#4825000
b11110001 $
b11110001 #
b11110001 %
#4830000
0"
#4840000
b11110001 '
1"
#4845000
b11110010 $
b11110010 #
b11110010 %
#4850000
0"
#4860000
b11110010 '
1"
#4865000
b11110011 $
b11110011 #
b11110011 %
#4870000
0"
#4880000
b11110011 '
1"
#4885000
b11110100 $
b11110100 #
b11110100 %
#4890000
0"
#4900000
b11110100 '
1"
#4905000
b11110101 $
b11110101 #
b11110101 %
#4910000
0"
#4920000
b11110101 '
1"
#4925000
b11110110 $
b11110110 #
b11110110 %
#4930000
0"
#4940000
b11110110 '
1"
#4945000
b11110111 $
b11110111 #
b11110111 %
#4950000
0"
#4960000
b11110111 '
1"
#4965000
b11111000 $
b11111000 #
b11111000 %
#4970000
0"
#4980000
b11111000 '
1"
#4985000
b11111001 $
b11111001 #
b11111001 %
#4990000
0"
#5000000
b11111001 '
1"
#5005000
b11111010 $
b11111010 #
b11111010 %
#5010000
0"
#5020000
b11111010 '
1"
#5025000
b11111011 $
b11111011 #
b11111011 %
#5030000
0"
#5040000
b11111011 '
1"
#5045000
b11111100 $
b11111100 #
b11111100 %
#5050000
0"
#5060000
b11111100 '
1"
#5065000
b11111101 $
b11111101 #
b11111101 %
#5070000
0"
#5080000
b11111101 '
1"
#5085000
b11111110 $
b11111110 #
b11111110 %
#5090000
0"
#5100000
b11111110 '
1"
#5105000
b11111111 $
b11111111 #
b11111111 %
#5110000
0"
#5120000
b11111111 '
1"
#5125000
b100000000 $
b100000000 #
b100000000 %
#5130000
0"
#5140000
b1111111 !
b1111111 &
b100000000 '
1"
#5145000
b100000001 $
b100000001 #
b100000001 %
#5150000
0"
#5160000
b1111110 !
b1111110 &
b100000001 '
1"
