Panchul/unit5/adder/adder.sv
module adder #(
    parameter WIDTH = 8
) (
    input   [WIDTH - 1 : 0] x,
    input   [WIDTH - 1 : 0] y,
    input   carry_in,
    output  [WIDTH - 1 : 0] z,
    output  carry_out
);

assign {carry_out, z} = x + y + carry_in;
    
endmodule

Panchul/unit5/adder/testbench.sv
`timescale 1ns / 1ps

module testbench;

parameter WIDTH = 8;

reg     c_in;
reg     [WIDTH - 1 : 0] x;
reg     [WIDTH - 1 : 0] y;
wire    [WIDTH - 1 : 0] z;
wire    c_out;

adder #(
    .WIDTH(WIDTH)
) adder_dut (
    .x(x),
    .y(y),
    .carry_in(c_in),
    .z(z),
    .carry_out(c_out)
);

//  test sequence
initial begin
    x = 0;
    y = 0;
    c_in = 0;
    #8;
    $finish;
end

initial forever begin
    #1;
    x = $urandom_range(0, 2**WIDTH - 1);
    y = $urandom_range(0, 2**WIDTH - 1);

    c_in = $urandom_range(0, 1);        
end

initial begin
    $dumpfile("wave.vcd");
    $dumpvars;
end

endmodule

Panchul/unit5/adder/wave.vcd
$date
	Thu Jul 30 16:22:59 2026
$end
$version
	Icarus Verilog
$end
$timescale
	1ps
$end
$scope module testbench $end
$var wire 8 ! z [7:0] $end
$var wire 1 " c_out $end
$var reg 1 # c_in $end
$var reg 8 $ x [7:0] $end
$var reg 8 % y [7:0] $end
$scope module adder_dut $end
$var wire 1 # carry_in $end
$var wire 8 & x [7:0] $end
$var wire 8 ' y [7:0] $end
$var wire 8 ( z [7:0] $end
$var wire 1 " carry_out $end
$upscope $end
$upscope $end
$enddefinitions $end
#0
$dumpvars
b0 (
b0 '
b0 &
b0 %
b0 $
0#
0"
b0 !
$end
#1000
b11010010 !
b11010010 (
b1000000 %
b1000000 '
b10010010 $
b10010010 &
#2000
b10111000 !
b10111000 (
1#
b10000110 %
b10000110 '
b110001 $
b110001 &
#3000
b111100 !
b111100 (
b1001 %
b1001 '
b110010 $
b110010 &
#4000
1"
b1000010 !
b1000010 (
b10111011 %
b10111011 '
b10000110 $
b10000110 &
#5000
b10111101 !
b10111101 (
b11000110 %
b11000110 '
b11110110 $
b11110110 &
#6000
0"
b11000101 !
b11000101 (
0#
b1100010 %
b1100010 '
b1100011 $
b1100011 &
#7000
b101101 !
b101101 (
1"
b111011 %
b111011 '
b11110010 $
b11110010 &
