Panchul/unit6/div_counter/div_counter.sv
module      div_counter #(
    parameter       CNT_DIV = 10
) (
    input       clk_in,
    input       rst_n,
    output      reg clk_out
);

//  внутренний регистр-счетчика
reg     [$clog2(CNT_DIV)-1 : 0] cnt;

//  комб логика
always @(*) begin
    clk_out = (cnt == 0);
end

//  посл логика
always @(posedge clk_in or negedge rst_n) begin
    if (!rst_n)
        cnt <= CNT_DIV - 1;
    else begin
        if  (cnt == 0)
            cnt <= CNT_DIV - 1;
        else
            cnt <= cnt - 1;
    end
end

endmodule

Panchul/unit6/div_counter/testbench.sv
`timescale 1ns / 1ps

module      testbench;

reg         clk_in;
reg         rst_n;
wire        clk_out;

initial begin
    $dumpfile("wave.vcd");
    $dumpvars;
end

div_counter #(
    .CNT_DIV(5)
) dut (
    .clk_in(clk_in),
    .rst_n(rst_n),
    .clk_out(clk_out)
);

initial begin
    clk_in = 0;
    forever begin
        #10; clk_in = ~clk_in;
    end
end

initial begin
    rst_n = 0;
    #32;
    rst_n = 1;
    #500;
    $display("TEST OK");
    $finish;
end

endmodule

Panchul/unit6/div_counter/wave.vcd
$date
	Thu Aug 13 05:39:52 2026
$end
$version
	Icarus Verilog
$end
$timescale
	1ps
$end
$scope module testbench $end
$var wire 1 ! clk_out $end
$var reg 1 " clk_in $end
$var reg 1 # rst_n $end
$scope module dut $end
$var wire 1 " clk_in $end
$var wire 1 # rst_n $end
$var reg 1 ! clk_out $end
$var reg 3 $ cnt [2:0] $end
$upscope $end
$upscope $end
$enddefinitions $end
#0
$dumpvars
b100 $
0#
0"
0!
$end
#10000
1"
#20000
0"
#30000
1"
#32000
1#
#40000
0"
#50000
b11 $
1"
#60000
0"
#70000
b10 $
1"
#80000
0"
#90000
b1 $
1"
#100000
0"
#110000
1!
b0 $
1"
#120000
0"
#130000
0!
b100 $
1"
#140000
0"
#150000
b11 $
1"
#160000
0"
#170000
b10 $
1"
#180000
0"
#190000
b1 $
1"
#200000
0"
#210000
1!
b0 $
1"
#220000
0"
#230000
0!
b100 $
1"
#240000
0"
#250000
b11 $
1"
#260000
0"
#270000
b10 $
1"
#280000
0"
#290000
b1 $
1"
#300000
0"
#310000
1!
b0 $
1"
#320000
0"
#330000
0!
b100 $
1"
#340000
0"
#350000
b11 $
1"
#360000
0"
#370000
b10 $
1"
#380000
0"
#390000
b1 $
1"
#400000
0"
#410000
1!
b0 $
1"
#420000
0"
#430000
0!
b100 $
1"
#440000
0"
#450000
b11 $
1"
#460000
0"
#470000
b10 $
1"
#480000
0"
#490000
b1 $
1"
#500000
0"
#510000
1!
b0 $
1"
#520000
0"
#530000
0!
b100 $
1"
