Panchul/unit7/stack_shift_reg/stack_shift_reg.sv
//  реализация стека с помощью сдвигового регистра
module      stack_shift_reg #(
    parameter   DATA_WIDTH = 8,
    parameter   STACK_SIZE = 4
) (
    //  сигнал тактирования
    input       clk,
    //  сигнал синхронного сброса
    input       reset,
    //  сигнал записи в стек
    input       push,
    //  сигнал чтения из стека
    input       pop,
    //  данные на входе стека
    input       [(DATA_WIDTH - 1) : 0] write_data,
    //  данные на выходе стека
    output      reg [(DATA_WIDTH - 1) : 0] read_data
);

//  непосредственно стек
reg             [(DATA_WIDTH - 1) : 0] stack[0 : (STACK_SIZE - 1)];

integer         i;

always  @(posedge clk) begin

    if (    reset) //   сигнал синхронного сброса
    begin
        for (   i = 0; i < STACK_SIZE; i = i + 1)
            stack[i] <= {DATA_WIDTH{1'b0}};
    end
    else if (   push) // сигнал записи
    begin
        //  сдвигаем стек вверх
        for (   i = 0; i < (STACK_SIZE - 1) ; i = i + 1)
            stack[i+1] <= stack[i];
        //  запись в вершину стека
        stack[0] <= write_data;
    end
    else if (   pop) // сигнал чтения 
    begin
        //  считываем вершину стека
        read_data <= stack[0];
        //  сдвигаем стек вниз
        for (   i = 0; i < (STACK_SIZE - 1) ; i = i + 1)
            stack[i] <= stack[i + 1];
        //  обнуляем "дно" стека
        stack[STACK_SIZE - 1] <= {DATA_WIDTH{1'b0}};
    end

end

endmodule

Panchul/unit7/stack_shift_reg/testbench.sv
`timescale 1ns / 1ns

module      testbench;

//  регистры для теста
reg         clk;
reg         reset;
reg         push;
reg         pop;
reg         [7:0] write_data;
wire        [7:0] read_data;

stack_shift_reg #(
    .STACK_SIZE(4),
    .DATA_WIDTH(8)
) dut (
    .clk(clk),
    .reset(reset),
    .push(push),
    .pop(pop),
    .write_data(write_data),
    .read_data(read_data)
);

initial begin
    $dumpfile("wave.vcd");
    $dumpvars;
end

initial begin
    //  начальные значения
    clk = 1;
    reset = 1;
    push = 1;
    pop = 0;
    write_data = 8'b00000000;

    //  запись
    #20;    write_data = 8'b00000001;
    #10;    reset = 0;
    #20;    write_data = 8'b00000010;
    #20;    write_data = 8'b00000011;
    #20;    write_data = 8'b00000100;
    #20;    write_data = 8'b00000101;
    #20;    write_data = 8'b00000110;
    push = 0;
    pop = 1;
    #20;    write_data = 8'b00000111;
    #20;    write_data = 8'b00001000;
    #20;    write_data = 8'b00001001;
    #20;    write_data = 8'b00001011;

end

//  тактирование
always  #10 clk = ~clk;

//  окончание
initial begin
    #220;
    $finish;
end

endmodule

Panchul/unit7/stack_shift_reg/wave.vcd
$date
	Tue Sep  8 20:30:29 2026
$end
$version
	Icarus Verilog
$end
$timescale
	1ns
$end
$scope module testbench $end
$var wire 8 ! read_data [7:0] $end
$var reg 1 " clk $end
$var reg 1 # pop $end
$var reg 1 $ push $end
$var reg 1 % reset $end
$var reg 8 & write_data [7:0] $end
$scope module dut $end
$var wire 1 " clk $end
$var wire 1 # pop $end
$var wire 1 $ push $end
$var wire 1 % reset $end
$var wire 8 ' write_data [7:0] $end
$var parameter 32 ( DATA_WIDTH $end
$var parameter 32 ) STACK_SIZE $end
$var reg 8 * read_data [7:0] $end
$var integer 32 + i [31:0] $end
$upscope $end
$upscope $end
$enddefinitions $end
$comment Show the parameter values. $end
$dumpall
b100 )
b1000 (
$end
#0
$dumpvars
b100 +
bx *
b0 '
b0 &
1%
1$
0#
1"
bx !
$end
#10
0"
#20
b100 +
1"
b1 &
b1 '
#30
0"
0%
#40
b11 +
1"
#50
0"
b10 &
b10 '
#60
b11 +
1"
#70
0"
b11 &
b11 '
#80
b11 +
1"
#90
0"
b100 &
b100 '
#100
b11 +
1"
#110
0"
b101 &
b101 '
#120
b11 +
1"
#130
0"
1#
0$
b110 &
b110 '
#140
b101 !
b101 *
b11 +
1"
#150
0"
b111 &
b111 '
#160
b100 !
b100 *
b11 +
1"
#170
0"
b1000 &
b1000 '
#180
b11 !
b11 *
b11 +
1"
#190
0"
b1001 &
b1001 '
#200
b10 !
b10 *
b11 +
1"
#210
0"
b1011 &
b1011 '
#220
b0 !
b0 *
b11 +
1"
