Panchul/unit6/preload_counter/preload_counter.sv
//  счетчик с предустановкой
module      preload_counter #(
    parameter       WIDTH = 8
) (
    input       clk,
    input       rst_n,
    input       load,
    input       [WIDTH - 1 : 0] data_load,
    output      reg [WIDTH - 1 : 0] cnt
);

always @(posedge clk or negedge rst_n) begin
    if  (!rst_n)
        cnt <= {WIDTH{1'b0}};
    else if (load)
        cnt <= data_load;
    else
        cnt <= cnt + 1'b1;
end

endmodule

Panchul/unit6/preload_counter/testbench.sv
`timescale 1ns / 1ps

module      testbench;

reg         clk;
reg         rst_n;
reg         load;
reg         [16 - 1 : 0] data_load;
wire        [16 - 1 : 0] cnt;

initial begin
    $dumpfile("wave.vcd");
    $dumpvars;
end

preload_counter #(
    .WIDTH(16)
) dut (
    .clk(clk),
    .rst_n(rst_n),
    .load(load),
    .data_load(data_load),
    .cnt(cnt)
);

initial begin
    clk = 0;
    forever begin
        #10; clk = ~clk;
    end
end

initial begin
    rst_n = 1;
    load = 0;
    data_load = 16'h0000;
    #15;
    rst_n = 0;
    #27;
    rst_n = 1;
    #3;
    #78;
    data_load = 16'h0ca9;
    #4;
    load = 1'b1;
    #10;
    load = 1'b0;

    #58;
    data_load = 16'h7877;
    #7;
    load = 1'b1;

    #10;
    load = 1'b0;

    #30;
    $display("TEST OK");
    $finish;
    
end



endmodule

Panchul/unit6/preload_counter/wave.vcd
$date
	Tue Aug 11 04:34:42 2026
$end
$version
	Icarus Verilog
$end
$timescale
	1ps
$end
$scope module testbench $end
$var wire 16 ! cnt [15:0] $end
$var reg 1 " clk $end
$var reg 16 # data_load [15:0] $end
$var reg 1 $ load $end
$var reg 1 % rst_n $end
$scope module dut $end
$var wire 1 " clk $end
$var wire 16 & data_load [15:0] $end
$var wire 1 $ load $end
$var wire 1 % rst_n $end
$var reg 16 ' cnt [15:0] $end
$upscope $end
$upscope $end
$enddefinitions $end
#0
$dumpvars
bx '
b0 &
1%
0$
b0 #
0"
bx !
$end
#10000
1"
#15000
b0 !
b0 '
0%
#20000
0"
#30000
1"
#40000
0"
#42000
1%
#50000
b1 !
b1 '
1"
#60000
0"
#70000
b10 !
b10 '
1"
#80000
0"
#90000
b11 !
b11 '
1"
#100000
0"
#110000
b100 !
b100 '
1"
#120000
0"
#123000
b110010101001 #
b110010101001 &
#127000
1$
#130000
b110010101001 !
b110010101001 '
1"
#137000
0$
#140000
0"
#150000
b110010101010 !
b110010101010 '
1"
#160000
0"
#170000
b110010101011 !
b110010101011 '
1"
#180000
0"
#190000
b110010101100 !
b110010101100 '
1"
#195000
b111100001110111 #
b111100001110111 &
#200000
0"
#202000
1$
#210000
b111100001110111 !
b111100001110111 '
1"
#212000
0$
#220000
0"
#230000
b111100001111000 !
b111100001111000 '
1"
