Panchul/unit5/carry_select_adder/testbench.sv
`timescale 1ns / 1ps

module      testbench;

reg     [31:0] x;
reg     [31:0] y;
reg     carry_in;
wire    [31:0] z;
wire    carry_out;

reg     [31:0] z_ideal;
reg     carry_out_ideal;

reg     [31:0] i;

initial begin
    $dumpfile("wave.vcd");
    $dumpvars;
end

carry_select_adder #(
    .BLOCK_COUNT(8),
    .BLOCK_SIZE(4)
) dut (
    .x(x),
    .y(y),
    .carry_in(carry_in),
    .z(z),
    .carry_out(carry_out)
);

initial begin
    for (i = 0; i < 50; i++) begin
        x = $random;
        y = $random;
        carry_in = $urandom_range(1, 0);

        {carry_out_ideal, z_ideal} = x + y + carry_in;

        #5;

        if ((carry_out_ideal != carry_out) ||
            (z_ideal != z)) begin
            $display("TEST FAILED\n");
            $finish;
        end

        #10;
    end

    $display("TEST OK\n");
    $finish;
end


endmodule

Panchul/unit5/carry_select_adder/carry_select_adder.sv
//  блок для сумматора с выбором переноса
//  размером 2 бита
module      carry_select_adder_block_2b(
    input   [1:0] x,
    input   [1:0] y,
    input   carry_in,
    output  [1:0] z,
    output  carry_out
);

wire    [1:0] sum_0;
wire    [1:0] sum_1;
wire    cout_1;
wire    cout_0;


assign {cout_0, sum_0} = x + y;
assign {cout_1, sum_1} = x + y + 1'b1;


assign carry_out = carry_in ? cout_1 : cout_0;
assign z = carry_in ? sum_1 : sum_0;

endmodule

//  блок для сумматора с выбором переноса
//  размером 4 бита
module      carry_select_adder_block_4b(
    input   [3:0] x,
    input   [3:0] y,
    input   carry_in,
    output  [3:0] z,
    output  carry_out
);

wire    [3:0] sum_0;
wire    [3:0] sum_1;
wire    cout_1;
wire    cout_0;


assign {cout_0, sum_0} = x + y;
assign {cout_1, sum_1} = x + y + 1'b1;


assign carry_out = carry_in ? cout_1 : cout_0;
assign z = carry_in ? sum_1 : sum_0;

endmodule

//  блок для сумматора с выбором переноса
//  размером 8 бит
module      carry_select_adder_block_8b(
    input   [7:0] x,
    input   [7:0] y,
    input   carry_in,
    output  [7:0] z,
    output  carry_out
);

wire    [7:0] sum_0;
wire    [7:0] sum_1;
wire    cout_1;
wire    cout_0;


assign {cout_0, sum_0} = x + y;
assign {cout_1, sum_1} = x + y + 1'b1;


assign carry_out = carry_in ? cout_1 : cout_0;
assign z = carry_in ? sum_1 : sum_0;

endmodule

//  блок для сумматора с выбором переноса
//  размером WIDTH бит
module      carry_select_adder_block #(
    parameter   WIDTH = 8
) (
    input   [WIDTH - 1 : 0] x,
    input   [WIDTH - 1 : 0] y,
    input   carry_in,
    output  [WIDTH - 1 : 0] z,
    output  carry_out
);

wire    [WIDTH - 1 : 0] sum_0;
wire    [WIDTH - 1 : 0] sum_1;
wire    cout_1;
wire    cout_0;


assign {cout_0, sum_0} = x + y;
assign {cout_1, sum_1} = x + y + 1'b1;


assign carry_out = carry_in ? cout_1 : cout_0;
assign z = carry_in ? sum_1 : sum_0;

endmodule

// ----------------------------------------------------
//  теперь сами сумматоры
//  пусть 8 бит использует 2 битные (4)
//  16 бит - 4 битные (4)
//  32 бит - 4 битные (8)
//  64 бит - 8 битные (8)


// ----------------------------------------------------
//  универсальный сумматор c выбором переноса
module      carry_select_adder #(
    //  количество блоков
    parameter   BLOCK_COUNT = 8,
    //  разрядность одного блока
    parameter   BLOCK_SIZE = 4
) (
    input   [BLOCK_COUNT * BLOCK_SIZE - 1 : 0] x,
    input   [BLOCK_COUNT * BLOCK_SIZE - 1 : 0] y,
    input   carry_in,
    output  [BLOCK_COUNT * BLOCK_SIZE - 1 : 0] z,
    output  carry_out
);

//  шина переносов, ее размер равен количеству блоков + 1
wire    [BLOCK_COUNT : 0] carry;

assign carry[0] = carry_in;

generate
    //  внутри будет BLOCK_COUNT блоков
    genvar i;
    for (i = 0; i < BLOCK_COUNT; i = i + 1) begin : stage
        carry_select_adder_block # (
            .WIDTH(BLOCK_SIZE)
        ) i_add_block(
            .x(x[(BLOCK_SIZE * (i + 1) - 1) : (BLOCK_SIZE * i)]),
            .y(y[(BLOCK_SIZE * (i + 1) - 1) : (BLOCK_SIZE * i)]),
            .carry_in(carry[i]),
            .z(z[(BLOCK_SIZE * (i + 1) - 1) : (BLOCK_SIZE * i)]),
            .carry_out(carry[i+1])
        );
    end

endgenerate

assign carry_out = carry[BLOCK_COUNT];

endmodule

Panchul/unit5/carry_select_adder/wave.vcd
$date
	Sat Aug  8 06:24:43 2026
$end
$version
	Icarus Verilog
$end
$timescale
	1ps
$end
$scope module carry_select_adder_block_2b $end
$var wire 1 ! carry_in $end
$var wire 2 " x [1:0] $end
$var wire 2 # y [1:0] $end
$var wire 2 $ z [1:0] $end
$var wire 2 % sum_1 [1:0] $end
$var wire 2 & sum_0 [1:0] $end
$var wire 1 ' cout_1 $end
$var wire 1 ( cout_0 $end
$var wire 1 ) carry_out $end
$upscope $end
$scope module carry_select_adder_block_4b $end
$var wire 1 * carry_in $end
$var wire 4 + x [3:0] $end
$var wire 4 , y [3:0] $end
$var wire 4 - z [3:0] $end
$var wire 4 . sum_1 [3:0] $end
$var wire 4 / sum_0 [3:0] $end
$var wire 1 0 cout_1 $end
$var wire 1 1 cout_0 $end
$var wire 1 2 carry_out $end
$upscope $end
$scope module carry_select_adder_block_8b $end
$var wire 1 3 carry_in $end
$var wire 8 4 x [7:0] $end
$var wire 8 5 y [7:0] $end
$var wire 8 6 z [7:0] $end
$var wire 8 7 sum_1 [7:0] $end
$var wire 8 8 sum_0 [7:0] $end
$var wire 1 9 cout_1 $end
$var wire 1 : cout_0 $end
$var wire 1 ; carry_out $end
$upscope $end
$scope module testbench $end
$var wire 32 < z [31:0] $end
$var wire 1 = carry_out $end
$var reg 1 > carry_in $end
$var reg 1 ? carry_out_ideal $end
$var reg 32 @ i [31:0] $end
$var reg 32 A x [31:0] $end
$var reg 32 B y [31:0] $end
$var reg 32 C z_ideal [31:0] $end
$scope module dut $end
$var wire 1 > carry_in $end
$var wire 32 D x [31:0] $end
$var wire 32 E y [31:0] $end
$var wire 32 F z [31:0] $end
$var wire 1 = carry_out $end
$var wire 9 G carry [8:0] $end
$scope begin stage[0] $end
$scope module i_add_block $end
$var wire 1 H carry_in $end
$var wire 4 I x [3:0] $end
$var wire 4 J y [3:0] $end
$var wire 4 K z [3:0] $end
$var wire 4 L sum_1 [3:0] $end
$var wire 4 M sum_0 [3:0] $end
$var wire 1 N cout_1 $end
$var wire 1 O cout_0 $end
$var wire 1 P carry_out $end
$upscope $end
$upscope $end
$scope begin stage[1] $end
$scope module i_add_block $end
$var wire 1 Q carry_in $end
$var wire 4 R x [3:0] $end
$var wire 4 S y [3:0] $end
$var wire 4 T z [3:0] $end
$var wire 4 U sum_1 [3:0] $end
$var wire 4 V sum_0 [3:0] $end
$var wire 1 W cout_1 $end
$var wire 1 X cout_0 $end
$var wire 1 Y carry_out $end
$upscope $end
$upscope $end
$scope begin stage[2] $end
$scope module i_add_block $end
$var wire 1 Z carry_in $end
$var wire 4 [ x [3:0] $end
$var wire 4 \ y [3:0] $end
$var wire 4 ] z [3:0] $end
$var wire 4 ^ sum_1 [3:0] $end
$var wire 4 _ sum_0 [3:0] $end
$var wire 1 ` cout_1 $end
$var wire 1 a cout_0 $end
$var wire 1 b carry_out $end
$upscope $end
$upscope $end
$scope begin stage[3] $end
$scope module i_add_block $end
$var wire 1 c carry_in $end
$var wire 4 d x [3:0] $end
$var wire 4 e y [3:0] $end
$var wire 4 f z [3:0] $end
$var wire 4 g sum_1 [3:0] $end
$var wire 4 h sum_0 [3:0] $end
$var wire 1 i cout_1 $end
$var wire 1 j cout_0 $end
$var wire 1 k carry_out $end
$upscope $end
$upscope $end
$scope begin stage[4] $end
$scope module i_add_block $end
$var wire 1 l carry_in $end
$var wire 4 m x [3:0] $end
$var wire 4 n y [3:0] $end
$var wire 4 o z [3:0] $end
$var wire 4 p sum_1 [3:0] $end
$var wire 4 q sum_0 [3:0] $end
$var wire 1 r cout_1 $end
$var wire 1 s cout_0 $end
$var wire 1 t carry_out $end
$upscope $end
$upscope $end
$scope begin stage[5] $end
$scope module i_add_block $end
$var wire 1 u carry_in $end
$var wire 4 v x [3:0] $end
$var wire 4 w y [3:0] $end
$var wire 4 x z [3:0] $end
$var wire 4 y sum_1 [3:0] $end
$var wire 4 z sum_0 [3:0] $end
$var wire 1 { cout_1 $end
$var wire 1 | cout_0 $end
$var wire 1 } carry_out $end
$upscope $end
$upscope $end
$scope begin stage[6] $end
$scope module i_add_block $end
$var wire 1 ~ carry_in $end
$var wire 4 !" x [3:0] $end
$var wire 4 "" y [3:0] $end
$var wire 4 #" z [3:0] $end
$var wire 4 $" sum_1 [3:0] $end
$var wire 4 %" sum_0 [3:0] $end
$var wire 1 &" cout_1 $end
$var wire 1 '" cout_0 $end
$var wire 1 (" carry_out $end
$upscope $end
$upscope $end
$scope begin stage[7] $end
$scope module i_add_block $end
$var wire 1 )" carry_in $end
$var wire 4 *" x [3:0] $end
$var wire 4 +" y [3:0] $end
$var wire 4 ," z [3:0] $end
$var wire 4 -" sum_1 [3:0] $end
$var wire 4 ." sum_0 [3:0] $end
$var wire 1 /" cout_1 $end
$var wire 1 0" cout_0 $end
$var wire 1 1" carry_out $end
$upscope $end
$upscope $end
$upscope $end
$upscope $end
$enddefinitions $end
#0
$dumpvars
01"
00"
0/"
b1101 ."
b1110 -"
b1101 ,"
b1100 +"
b1 *"
0)"
0("
0'"
0&"
b10 %"
b11 $"
b10 #"
b0 ""
b10 !"
0~
0}
0|
0{
b1001 z
b1010 y
b1001 x
b1000 w
b1 v
0u
0t
0s
0r
b1110 q
b1111 p
b1110 o
b1001 n
b101 m
0l
0k
0j
0i
b1000 h
b1001 g
b1001 f
b101 e
b11 d
1c
1b
1a
1`
b11 _
b100 ^
b11 ]
b1110 \
b101 [
0Z
0Y
0X
0W
b1010 V
b1011 U
b1010 T
b1000 S
b10 R
0Q
0P
0O
0N
b101 M
b110 L
b110 K
b1 J
b100 I
1H
b1001 G
b11010010100111101001001110100110 F
b11000000100010010101111010000001 E
b10010000101010011010100100100 D
b11010010100111101001001110100110 C
b11000000100010010101111010000001 B
b10010000101010011010100100100 A
b0 @
0?
1>
0=
b11010010100111101001001110100110 <
x;
x:
x9
bx 8
bx 7
bx 6
bz 5
bz 4
z3
x2
x1
x0
bx /
bx .
bx -
bz ,
bz +
z*
x)
x(
x'
bx &
bx %
bx $
bz #
bz "
z!
$end
#15000
0c
1l
1~
1=
0b
b110 T
b1100 ]
b10 f
1k
b101 o
b111 x
1}
b110 #"
b11 ,"
11"
b110110011101010010110001101100 <
b110110011101010010110001101100 F
b1100 K
0a
0`
b1100 M
b1101 L
b110 V
b111 U
b1100 _
b1101 ^
b10 h
1j
b11 g
1i
b100 q
b101 p
b111 z
1|
b1000 y
1{
b101 %"
b110 $"
b11 ."
10"
b100 -"
1/"
0H
b11 J
b110 S
b110 \
b0 n
b1111 w
b1 ""
b1011 +"
b1001 I
b0 R
b110 [
b1101 d
b100 m
b1000 v
b100 !"
b1000 *"
1?
b110110011101010010110001101100 C
b101010000 G
0>
b10110001111100000101011001100011 B
b10110001111100000101011001100011 E
b10000100100001001101011000001001 A
b10000100100001001101011000001001 D
b1 @
#30000
1u
1Q
1c
0=
b1001 T
1t
b1010 K
1P
b100 ]
1b
b1 f
b1001 o
b1001 x
b1101 #"
b1001101100110010001010010011010 <
b1001101100110010001010010011010 F
b100 ,"
b1111010 G
01"
b1000 V
b1001 U
1s
1r
b1010 M
1O
b1011 L
1N
b100 _
1a
b101 ^
1`
b0 h
b1 g
b1000 q
b1001 p
b1000 z
b1001 y
b1100 %"
b1101 $"
b100 ."
00"
b101 -"
0/"
b1101 J
b1000 S
b1001 \
b1001 e
b1111 n
b1101 w
b110 ""
b100 +"
b1101 I
b1011 [
b111 d
b1001 m
b1011 v
b110 !"
b0 *"
0?
b1001101100110010001010010011010 C
b1000110110111111001100110001101 B
b1000110110111111001100110001101 E
b110101110010111101100001101 A
b110101110010111101100001101 D
b10 @
#45000
0~
0}
0Q
0l
0u
1=
0c
0P
0k
0t
11"
b111 K
b111 T
b110 ]
b100000000 G
0b
b1101 f
b1001 o
b1111 x
b1011 #"
b111011111110011101011001110111 <
b111011111110011101011001110111 F
b11 ,"
0O
0N
0j
0i
0s
0r
0|
10"
b111 M
b1000 L
b111 V
b1000 U
b110 _
0a
b111 ^
0`
b1101 h
b1110 g
b1001 q
b1010 p
b1111 z
b0 y
b1011 %"
b1100 $"
b11 ."
b100 -"
1/"
b10 J
b1 S
b10 \
b101 e
b111 n
b11 w
b1001 ""
b1000 +"
b101 I
b110 R
b100 [
b1000 d
b10 m
b1100 v
b10 !"
b1011 *"
1?
b111011111110011101011001110111 C
b10001001001101110101001000010010 B
b10001001001101110101001000010010 E
b10110010110000101000010001100101 A
b10110010110000101000010001100101 D
b11 @
#60000
1c
1l
1~
0=
1b
b0 T
b0 ]
b1011 f
1k
b1011 o
b1100 x
1}
b111 #"
b0 ,"
01"
b111110010111011000000001111 <
b111110010111011000000001111 F
b1111 K
1a
1`
b1110 M
b1111 L
b0 V
b1 U
b0 _
b1 ^
b1010 h
1j
b1011 g
1i
b1010 q
b1011 p
b1100 z
1|
b1101 y
b110 %"
b111 $"
b0 ."
00"
b1 -"
0/"
1H
b1101 J
b0 S
b1101 \
b1100 e
b1101 w
b110 ""
b0 +"
b1 I
b0 R
b11 [
b1110 d
b11 m
b1111 v
b0 !"
b0 *"
0?
b111110010111011000000001111 C
b1011001 G
1>
b110110101111100110100001101 B
b110110101111100110100001101 E
b111100111110001100000001 A
b111100111110001100000001 D
b100 @
#75000
1u
1Q
0c
0~
1)"
b1 o
1t
b100 K
1P
b1011 T
b1110 ]
0b
b1011 f
b1011 x
0}
b1001 #"
b10110011 G
1("
b1011001101100011011111010110100 <
b1011001101100011011111010110100 F
b101 ,"
b0 q
1s
b1 p
1r
0{
b11 M
1O
b100 L
1N
b1010 V
b1011 U
b1110 _
0a
b1111 ^
0`
b1011 h
b1100 g
b1010 z
0|
b1011 y
b1001 %"
1'"
b1010 $"
1&"
b100 ."
b101 -"
b11 S
b1101 n
b1000 w
b1110 ""
b1 +"
b110 I
b111 R
b1 [
b1111 d
b10 v
b1011 !"
b11 *"
b1011001101100011011111010110100 C
b11110100011011100110100111101 B
b11110100011011100110100111101 E
b111011001000111111000101110110 A
b111011001000111111000101110110 D
b101 @
#90000
b1111 ]
0)"
1Z
1~
0("
b111 T
1Y
b100 f
b10 o
b0 x
1}
b1101 #"
b1011 ,"
b10111101000000100100111101111001 <
b10111101000000100100111101111001 F
b1001 K
0'"
0&"
b1001 M
b1010 L
b110 V
1X
b111 U
1W
b100 h
b101 g
b1 q
b10 p
b1111 z
b0 y
1{
b1100 %"
b1101 $"
b1011 ."
b1100 -"
0H
b1100 J
b1000 S
b111 \
b1111 e
b10 w
b110 ""
b100 +"
b1101 I
b1110 R
b111 [
b101 d
b100 m
b1101 v
b110 !"
b111 *"
b10111101000000100100111101111001 C
b1110110 G
0>
b1000110001011011111011110001100 B
b1000110001011011111011110001100 E
b1110110110101000101011111101101 A
b1110110110101000101011111101101 D
b110 @
#105000
0Q
1=
1)"
0P
b110 ,"
11"
b1111 K
b1011 T
b1110 ]
b0 f
b101 o
b11 x
b1100000001101010000111010111111 <
b1100000001101010000111010111111 F
b0 #"
b111110100 G
1("
0O
b101 ."
10"
b110 -"
1/"
b1111 M
b0 L
b1011 V
b1100 U
b1101 _
b1110 ^
b0 h
b1 g
b100 q
b101 p
b10 z
1|
b11 y
b1111 %"
b0 $"
1&"
b110 J
b1100 S
b100 \
b10 e
b111 n
b11 w
b11 ""
b1110 +"
b1001 I
b1111 R
b1001 [
b1110 d
b1101 m
b1111 v
b1100 !"
1?
b1100000001101010000111010111111 C
b11100011001101110010010011000110 B
b11100011001101110010010011000110 E
b1111100111111011110100111111001 A
b1111100111111011110100111111001 D
b111 @
#120000
0u
0)"
1Q
b0 x
b111 T
b111 ]
b101 f
b1011 o
0t
b1000 #"
0("
b1011 ,"
1P
b10111000000010110101011101110000 <
b10111000000010110101011101110000 F
b0 K
b0 z
b1 y
b110 V
b111 U
b110 _
b111 ^
b101 h
b110 g
b1010 q
0s
b1011 p
0r
b111 %"
b1000 $"
0&"
b1011 ."
b1100 -"
1H
b1010 J
b1010 S
b10 \
b1101 e
b11 n
b1 w
b101 ""
b1101 +"
b101 I
b1100 R
b100 [
b1000 d
b111 m
b10 !"
b1110 *"
b10111000000010110101011101110000 C
b101010111 G
1>
b11010101000100111101001010101010 B
b11010101000100111101001010101010 E
b11100010111101111000010011000101 A
b11100010111101111000010011000101 D
b1000 @
#135000
0Q
1u
b1101 K
0P
b1110 #"
b101 T
b1010 ]
b110 f
b10 o
b101110101 G
1t
b1000 x
b101110100000100110101001011101 <
b101110100000100110101001011101 F
b10 ,"
b1100 M
b1101 L
0N
b1101 %"
b1110 $"
b101 V
b110 U
b1001 _
b1010 ^
b110 h
b111 g
b1 q
1s
b10 p
1r
b111 z
b1000 y
b10 ."
b11 -"
b111 J
b111 S
b111 e
b10 n
b1101 w
b1011 ""
b1011 +"
b1110 R
b111 [
b1111 d
b1111 m
b1010 v
b111 *"
b101110100000100110101001011101 C
b10111011110100100111001001110111 B
b10111011110100100111001001110111 E
b1110010101011111111011111100101 A
b1110010101011111111011111100101 D
b1001 @
#150000
1Q
1c
0=
0Z
0u
1)"
1P
1b
01"
b10 K
b1010 T
0Y
b1 ]
b1011 f
b1111 o
0t
b1 x
b1 #"
b11011011 G
1("
b11010001000111111011000110100010 <
b11010001000111111011000110100010 F
b1101 ,"
1O
1N
1a
1`
00"
0/"
b1 M
b10 L
b1001 V
0X
b1010 U
0W
b1 _
b10 ^
b1010 h
b1011 g
b1110 q
0s
b1111 p
0r
b1 z
b10 y
b0 %"
1'"
b1 $"
1&"
b1100 ."
b1101 -"
b1111 J
b1000 S
b1011 \
b1101 e
b1100 n
b1110 w
b111 ""
b100 +"
b10 I
b1 R
b110 [
b1101 d
b10 m
b11 v
b1001 !"
b1000 *"
0?
b11010001000111111011000110100010 C
b1000111111011001101101110001111 B
b1000111111011001101101110001111 E
b10001001001100101101011000010010 A
b10001001001100101101011000010010 D
b1010 @
#165000
1l
1k
b0 #"
1c
0~
1=
1Z
b1 K
1b
b1010 x
0}
11"
b1100 T
b110011111 G
1Y
b0 ]
b0 f
b111 o
b1100000101001110000000011000001 <
b1100000101001110000000011000001 F
b110 ,"
b0 M
b1 L
0a
0j
b1010 z
0|
b1011 y
0{
10"
1/"
b1011 V
1X
b1100 U
1W
b1111 _
b0 ^
b1111 h
b0 g
b110 q
b111 p
b101 ."
b110 -"
b1110 J
b1100 S
b110 \
b1001 e
b110 n
b111 w
b1110 +"
b1111 R
b1001 [
b110 d
b0 m
b111 *"
1?
b1100000101001110000000011000001 C
b11100111011101101001011011001110 B
b11100111011101101001011011001110 E
b1111001001100000110100111110010 A
b1111001001100000110100111110010 D
b1011 @
#180000
0Q
0l
0)"
0P
0k
b1010 o
b1110 K
b1010 T
b1001 ]
b1100 f
b1100 x
b110 #"
b100001101 G
0("
b11010110110010101100100110101110 <
b11010110110010101100100110101110 F
b1101 ,"
0O
0N
0i
b1010 q
b1011 p
b1101 M
b1110 L
b1010 V
b1011 U
b1000 _
1a
b1001 ^
b1011 h
b1100 g
b1100 z
b1101 y
b110 %"
0'"
b111 $"
0&"
b1101 ."
b1110 -"
b101 J
b1110 \
b100 e
b1010 n
b1100 w
b10 ""
b1000 I
b1110 R
b1010 [
b111 d
b0 v
b100 !"
b1111 *"
b11010110110010101100100110101110 C
b11100010110010100100111011000101 B
b11100010110010100100111011000101 E
b11110100000000000111101011101000 A
b11110100000000000111101011101000 D
b1100 @
#195000
1=
1Q
1u
1)"
11"
b1010 K
1P
b1 T
b10 ]
b111 f
b110 o
1t
b1110 x
b1100 #"
b110101111 G
1("
b1100111001100111001000011010 <
b1100111001100111001000011010 F
b0 ,"
00"
b1001 M
1O
b1010 L
1N
b0 V
b1 U
b1 _
b10 ^
b110 h
b111 g
b110 q
1s
b111 p
1r
b1101 z
b1110 y
b1100 %"
1'"
b1101 $"
1&"
b1111 ."
b0 -"
b1101 J
b1011 S
b1000 \
b10 e
b1110 n
b1000 w
b1110 ""
b1101 +"
b1100 I
b101 R
b1001 [
b100 d
b1000 m
b101 v
b1110 !"
b10 *"
b1100111001100111001000011010 C
b11011110100011100010100010111101 B
b11011110100011100010100010111101 E
b101110010110000100100101011100 A
b101110010110000100100101011100 D
b1101 @
#210000
0c
0)"
0Z
1~
0b
0("
b11 K
b1001 T
0Y
b1110 ]
b111 f
b10 o
b101 x
b101100011 G
1}
b1001 #"
b1001001010100100111111010010011 <
b1001001010100100111111010010011 F
b100 ,"
0a
0`
0'"
0&"
b10 M
b11 L
b1000 V
0X
b1001 U
0W
b1110 _
b1111 ^
b111 h
b1000 g
b10 q
b11 p
b100 z
1|
b101 y
1{
b1000 %"
b1001 $"
b100 ."
10"
b101 -"
b101 J
b110 S
b110 \
b111 n
b1010 w
b10 ""
b1011 +"
b1101 I
b10 R
b1000 [
b101 d
b1011 m
b1010 v
b110 !"
b1001 *"
b1001001010100100111111010010011 C
b10110010101001110010011001100101 B
b10110010101001110010011001100101 E
b10010110101010110101100000101101 A
b10010110101010110101100000101101 D
b1110 @
#225000
0=
0Q
01"
b110 T
b1001 ]
b1110 f
b110 x
b111 #"
b1011 ,"
0P
b10110111011000101110100101101101 <
b10110111011000101110100101101101 F
b1101 K
00"
0/"
b1101 M
0O
b1110 L
0N
b110 V
b111 U
b1001 _
b1010 ^
b1110 h
b1111 g
b101 z
b110 y
b110 %"
b111 $"
b1011 ."
b1100 -"
0H
b1010 J
b0 S
b111 \
b1000 e
b11 n
b111 w
b101 ""
b0 +"
b11 I
b110 R
b10 [
b110 d
b1111 m
b1110 v
b1 !"
b1011 *"
0?
b10110111011000101110100101101101 C
b1100000 G
0>
b101011100111000011100001010 B
b101011100111000011100001010 E
b10110001111011110110001001100011 A
b10110001111011110110001001100011 D
b1111 @
#240000
0u
0~
b11 ]
b0 K
b1010 T
b100 f
b1111 o
0t
b1001 x
b0 G
0}
b0 #"
b11010000100111110100001110100000 <
b11010000100111110100001110100000 F
b1101 ,"
b11 _
b100 ^
b0 M
b1 L
b1010 V
b1011 U
b100 h
b101 g
b1111 q
0s
b0 p
b1001 z
0|
b1010 y
0{
b0 %"
b1 $"
b1101 ."
b1110 -"
b0 J
b10 S
b1 \
b10 e
b100 n
b110 w
b0 ""
b1 +"
b0 I
b1000 R
b10 d
b1011 m
b11 v
b0 !"
b1100 *"
b11010000100111110100001110100000 C
b10000011001000010000100100000 B
b10000011001000010000100100000 E
b11000000001110110010001010000000 A
b11000000001110110010001010000000 D
b10000 @
#255000
1Q
1Z
1c
1l
1u
1~
1)"
1=
1P
1Y
1b
1k
1t
1}
1("
b111111110 G
11"
b111 K
b100 T
b10 ]
b1 f
b101 o
b100 x
b100 #"
b100100010001010001001001000111 <
b100100010001010001001001000111 F
b10 ,"
1O
1N
1X
1W
1a
1`
1j
1i
1s
1|
1{
1'"
1&"
10"
1/"
b111 M
b1000 L
b11 V
b100 U
b1 _
b10 ^
b0 h
b1 g
b100 q
b101 p
b11 z
b100 y
b11 %"
b100 $"
b1 ."
b10 -"
b1101 J
b1001 S
b1100 \
b1100 e
b1100 n
b1100 w
b1110 ""
b1100 +"
b1010 I
b1010 R
b101 [
b100 d
b1000 m
b111 v
b101 !"
b101 *"
1?
b100100010001010001001001000111 C
b11001110110011001100110010011101 B
b11001110110011001100110010011101 E
b1010101011110000100010110101010 A
b1010101011110000100010110101010 D
b10001 @
#270000
0Z
0l
0u
0~
0Q
0Y
0k
b1010 T
b110 ]
b1111 f
b11 o
0t
b1010 x
0}
b100 #"
b101 ,"
0P
b1010100101000111111011010101010 <
b1010100101000111111011010101010 F
b1010 K
0O
0N
0X
0W
0i
b1001 M
b1010 L
b1010 V
b1011 U
b110 _
b111 ^
b1110 h
0j
b1111 g
b11 q
0s
b100 p
0r
b1010 z
0|
b1011 y
0{
b100 %"
b101 $"
b100 ."
b101 -"
1H
b11 J
b1 S
b1000 \
b1011 e
b11 n
b1000 w
b1001 ""
b1000 +"
b110 I
b1001 R
b1110 [
b11 d
b0 m
b10 v
b1011 !"
b1100 *"
b1010100101000111111011010101010 C
b110001001 G
1>
b10001001100000111011100000010011 B
b10001001100000111011100000010011 E
b11001011001000000011111010010110 A
b11001011001000000011111010010110 D
b10010 @
#285000
b100 o
0c
1l
1u
1~
1)"
1Q
0b
b0 f
1k
1t
b110 T
b1110 ]
b110 x
1}
b0 #"
1("
b11 ,"
1P
b110000011001000000111001100000 <
b110000011001000000111001100000 F
b0 K
0a
0`
b0 h
1j
b1 g
1i
1s
b0 M
1O
b1 L
1N
b101 V
b110 U
b1110 _
b1111 ^
1r
b101 z
1|
b110 y
1{
b1111 %"
0'"
b0 $"
b10 ."
b11 -"
0H
b101 S
b110 \
b1101 e
b111 n
b1010 w
b1010 +"
b1101 I
b0 R
b1000 [
b1100 m
b1011 v
b110 !"
b1000 *"
b110000011001000000111001100000 C
b111110010 G
0>
b10101001101001111101011001010011 B
b10101001101001111101011001010011 E
b10000110101111000011100000001101 A
b10000110101111000011100000001101 D
b10011 @
#300000
1Z
1l
1c
1Y
1k
b100 T
b1000 ]
b111111110 G
1b
b0 f
b110 o
b100 x
b100000010001100000100001000000 <
b100000010001100000100001000000 F
b10 ,"
1X
1W
0j
b11 V
b100 U
b111 _
1a
b1000 ^
1`
b1111 h
b0 g
b101 q
b110 p
b11 z
b100 y
b1 ."
b10 -"
b101 J
b1101 S
b1010 \
b10 e
b110 n
b1010 ""
b1110 +"
b1011 I
b110 R
b1101 [
b1101 d
b1111 m
b1001 v
b101 !"
b11 *"
b100000010001100000100001000000 C
b11101010101001100010101011010101 B
b11101010101001100010101011010101 E
b110101100111111101110101101011 A
b110101100111111101110101101011 D
b10100 @
#315000
0Z
0l
0u
0~
0)"
b1011 T
0Y
b1000 ]
b1000 f
0k
b1101 o
0t
b110 x
0}
b1000 #"
0("
b101 ,"
b1011000011011011000100010110001 <
b1011000011011011000100010110001 F
b1 K
b1010 V
0X
b1011 U
0W
b1000 _
b1001 ^
b111 h
b1000 g
0i
b1101 q
0s
b1110 p
0r
b110 z
0|
b111 y
0{
b1000 %"
b1001 $"
0&"
b101 ."
b110 -"
1H
b1110 J
b1010 S
b1110 \
b11 e
b101 w
b111 ""
b1101 +"
b10 I
b0 R
b1010 [
b100 d
b111 m
b1 v
b1 !"
b1000 *"
b1011000011011011000100010110001 C
b100001011 G
1>
b11010111010101100011111010101110 B
b11010111010101100011111010101110 E
b10000001000101110100101000000010 A
b10000001000101110100101000000010 D
b10101 @
#330000
0c
1l
1u
1~
1)"
0=
0b
b1101 K
b1110 T
b1011 ]
b101 f
1k
b101 o
1t
b1100 x
1}
b110 #"
1("
b11110110110001010101101111101101 <
b11110110110001010101101111101101 F
b1111 ,"
b11110011 G
01"
0a
0`
b1100 M
b1101 L
b1101 V
b1110 U
b1011 _
b1100 ^
b101 h
1j
b110 g
1i
b100 q
1s
b101 p
1r
b1011 z
1|
b1100 y
1{
b101 %"
1'"
b110 $"
1&"
b1110 ."
00"
b1111 -"
0/"
b1111 J
b1100 S
b10 \
b111 e
b101 n
b1100 w
b1110 +"
b1101 I
b1 R
b1001 [
b1110 d
b1111 m
b1111 v
b1110 !"
b0 *"
0?
b11110110110001010101101111101101 C
b11100111110001010111001011001111 B
b11100111110001010111001011001111 E
b1110111111111110100100011101 A
b1110111111111110100100011101 D
b10110 @
#345000
0~
0l
0u
0)"
0Q
b1110 ]
0}
b10 T
b1010 f
0k
b1101 o
0t
b1000 x
b110 #"
0("
b10110100011011010111000101101 <
b10110100011011010111000101101 F
b1 ,"
0P
0O
0N
b1110 _
b1111 ^
0|
0{
b1101 M
b1110 L
b10 V
b11 U
b1010 h
0j
b1011 g
0i
b1101 q
0s
b1110 p
0r
b1000 z
b1001 y
b110 %"
0'"
b111 $"
0&"
b1 ."
b10 -"
0H
b1010 J
b0 S
b101 \
b110 e
b1001 n
b0 w
b101 ""
b0 +"
b11 I
b10 R
b100 d
b100 m
b1000 v
b1 !"
b1 *"
b10110100011011010111000101101 C
b0 G
0>
b101000010010110010100001010 B
b101000010010110010100001010 E
b10001100001000100100100100011 A
b10001100001000100100100100011 D
b10111 @
#360000
1Z
1Y
1c
1)"
1=
1Q
1b
1("
11"
b110 K
b110001110 G
1P
b0 T
b111 ]
b101 f
b100 o
b1010 x
b11 #"
b10000011101001000101011100000110 <
b10000011101001000101011100000110 F
b1000 ,"
1W
1a
1'"
1&"
10"
1/"
b110 M
1O
b111 L
1N
b1111 V
b0 U
b110 _
b111 ^
1`
b100 h
b101 g
b100 q
b101 p
b1010 z
b1011 y
b11 %"
b100 $"
b111 ."
b1000 -"
b1100 J
b11 S
b1100 \
b100 e
b1 n
b11 w
b1110 ""
b1001 +"
b1010 I
b1100 R
b1010 [
b0 d
b11 m
b111 v
b101 !"
b1110 *"
1?
b10000011101001000101011100000110 C
b10011110001100010100110000111100 B
b10011110001100010100110000111100 E
b11100101011100110000101011001010 A
b11100101011100110000101011001010 D
b11000 @
