Panchul/unit5/shifter/right_rotator.sv
module  right_rotator #(
    parameter WIDTH = 8,
    parameter SHIFT = 3
) (
    input   [WIDTH-1 : 0] x,
    input   [SHIFT-1 : 0] shamt,
    output  [WIDTH-1 : 0] z
);

wire    [2 * WIDTH - 1 : 0] temp;
assign temp = {x, x} >> shamt;
assign z = temp[WIDTH - 1 : 0];

endmodule

Panchul/unit5/shifter/left_rotator.sv
module  left_rotator #(
    parameter WIDTH = 8,
    parameter SHIFT = 3
) (
    input   [WIDTH-1 : 0] x,
    input   [SHIFT-1 : 0] shamt,
    output  [WIDTH-1 : 0] z
);

wire    [2 * WIDTH - 1 : 0] temp;
assign temp = {x, x} << shamt;
assign z = temp[2*WIDTH - 1 : WIDTH];

endmodule

Panchul/unit5/shifter/right_shifter.sv
module  right_shifter #(
    parameter WIDTH = 8,
    parameter SHIFT = 3
) (
    input   [WIDTH-1 : 0] x,
    input   [SHIFT-1 : 0] shamt,
    output  [WIDTH-1 : 0] z
);

assign z = x >> shamt;

endmodule

Panchul/unit5/shifter/left_shifter.sv
module  left_shifter #(
    parameter WIDTH = 8,
    parameter SHIFT = 3
) (
    input   [WIDTH-1 : 0] x,
    input   [SHIFT-1 : 0] shamt,
    output  [WIDTH-1 : 0] z
);

assign z = x << shamt;

endmodule

Panchul/unit5/shifter/testbench.sv
`timescale 1ns / 1ps

module  testbench;

reg     [7:0] x;
reg     [2:0] shamt;
wire    [7:0] y_lsh;
wire    [7:0] y_rsh;
wire    [7:0] y_lrot;
wire    [7:0] y_rrot;

initial begin
    $dumpfile("wave.vcd");
    $dumpvars;
end

left_shifter #(
    .WIDTH(8),
    .SHIFT(3))
dut1 (
    .x(x),
    .shamt(shamt),
    .z(y_lsh)
);

right_shifter #(
    .WIDTH(8),
    .SHIFT(3))
dut2 (
    .x(x),
    .shamt(shamt),
    .z(y_rsh)
);

left_rotator #(
    .WIDTH(8),
    .SHIFT(3))
dut3 (
    .x(x),
    .shamt(shamt),
    .z(y_lrot)
);

right_rotator #(
    .WIDTH(8),
    .SHIFT(3))
dut4 (
    .x(x),
    .shamt(shamt),
    .z(y_rrot)
);

initial begin
    x = 8'b00000000;
    shamt = 3'b000;
    #10;
    x = 8'b11100111;
    shamt = 3'b100;
    #10;
    x = 8'b10011100;
    #10;
    x = 8'b11101000;
    shamt = 3'b111;
    #10;
    x = 8'b00010110;
    shamt = 3'b100;
    #10;
    x = 8'b00000000;
    shamt = 3'b001;
    #10;
    x = 8'b11111000;
    shamt = 3'b011;
    #10;
    x = 8'b00010001;
    shamt = 3'b010;
    #10;
    $finish;
end

endmodule

Panchul/unit5/shifter/wave.vcd
$date
	Thu Jul 30 18:03:17 2026
$end
$version
	Icarus Verilog
$end
$timescale
	1ps
$end
$scope module testbench $end
$var wire 8 ! y_rsh [7:0] $end
$var wire 8 " y_rrot [7:0] $end
$var wire 8 # y_lsh [7:0] $end
$var wire 8 $ y_lrot [7:0] $end
$var reg 3 % shamt [2:0] $end
$var reg 8 & x [7:0] $end
$scope module dut1 $end
$var wire 3 ' shamt [2:0] $end
$var wire 8 ( x [7:0] $end
$var wire 8 ) z [7:0] $end
$upscope $end
$scope module dut2 $end
$var wire 3 * shamt [2:0] $end
$var wire 8 + x [7:0] $end
$var wire 8 , z [7:0] $end
$upscope $end
$scope module dut3 $end
$var wire 3 - shamt [2:0] $end
$var wire 8 . x [7:0] $end
$var wire 8 / z [7:0] $end
$var wire 16 0 temp [15:0] $end
$upscope $end
$scope module dut4 $end
$var wire 3 1 shamt [2:0] $end
$var wire 8 2 x [7:0] $end
$var wire 8 3 z [7:0] $end
$var wire 16 4 temp [15:0] $end
$upscope $end
$upscope $end
$enddefinitions $end
#0
$dumpvars
b0 4
b0 3
b0 2
b0 1
b0 0
b0 /
b0 .
b0 -
b0 ,
b0 +
b0 *
b0 )
b0 (
b0 '
b0 &
b0 %
b0 $
b0 #
b0 "
b0 !
$end
#10000
b1111110 $
b1111110 /
b1111110 "
b1111110 3
b100 %
b100 '
b100 *
b100 -
b100 1
b1110000 #
b1110000 )
b1110 !
b1110 ,
b111111001110000 0
b111001111110 4
b11100111 &
b11100111 (
b11100111 +
b11100111 .
b11100111 2
#20000
b11001001 $
b11001001 /
b11001001 "
b11001001 3
b11000000 #
b11000000 )
b1001 !
b1001 ,
b1100100111000000 0
b100111001001 4
b10011100 &
b10011100 (
b10011100 +
b10011100 .
b10011100 2
#30000
b1110100 $
b1110100 /
b11010001 "
b11010001 3
b111 %
b111 '
b111 *
b111 -
b111 1
b0 #
b0 )
b1 !
b1 ,
b111010000000000 0
b111010001 4
b11101000 &
b11101000 (
b11101000 +
b11101000 .
b11101000 2
#40000
b1100001 $
b1100001 /
b1100001 "
b1100001 3
b1100000 #
b1100000 )
b100 %
b100 '
b100 *
b100 -
b100 1
b1 !
b1 ,
b110000101100000 0
b101100001 4
b10110 &
b10110 (
b10110 +
b10110 .
b10110 2
#50000
b0 $
b0 /
b0 "
b0 3
b1 %
b1 '
b1 *
b1 -
b1 1
b0 #
b0 )
b0 !
b0 ,
b0 0
b0 4
b0 &
b0 (
b0 +
b0 .
b0 2
#60000
b11000111 $
b11000111 /
b11111 "
b11111 3
b11 %
b11 '
b11 *
b11 -
b11 1
b11000000 #
b11000000 )
b11111 !
b11111 ,
b1100011111000000 0
b1111100011111 4
b11111000 &
b11111000 (
b11111000 +
b11111000 .
b11111000 2
#70000
b1000100 $
b1000100 /
b1000100 "
b1000100 3
b10 %
b10 '
b10 *
b10 -
b10 1
b1000100 #
b1000100 )
b100 !
b100 ,
b100010001000100 0
b10001000100 4
b10001 &
b10001 (
b10001 +
b10001 .
b10001 2
